[{"text":"A","x":138,"y":153,"w":22,"h":22,"orientation":"horizontal"},{"text":"m","x":142,"y":441,"w":14,"h":22,"orientation":"vertical"},{"text":"PID","x":181,"y":438,"w":25,"h":43,"orientation":"vertical"},{"text":"-","x":181,"y":419,"w":25,"h":17,"orientation":"vertical"},{"text":"0000","x":181,"y":346,"w":27,"h":69,"orientation":"vertical"},{"text":"0","x":140,"y":730,"w":14,"h":20,"orientation":"horizontal"},{"text":"\u05d5\u05d9\u05d5","x":143,"y":1309,"w":13,"h":23,"orientation":"vertical"},{"text":"NOTES","x":4028,"y":232,"w":105,"h":26,"orientation":"horizontal"},{"text":"16","x":4630,"y":66,"w":36,"h":21,"orientation":"horizontal"},{"text":"Aker","x":4270,"y":138,"w":132,"h":43,"orientation":"horizontal"},{"text":"Solutions","x":4401,"y":138,"w":241,"h":43,"orientation":"horizontal"},{"text":"\u2122","x":4627,"y":138,"w":22,"h":43,"orientation":"horizontal"},{"text":"1","x":308,"y":67,"w":12,"h":21,"orientation":"horizontal"},{"text":"2","x":590,"y":65,"w":24,"h":24,"orientation":"horizontal"},{"text":"3","x":883,"y":65,"w":21,"h":22,"orientation":"horizontal"},{"text":"4","x":1169,"y":68,"w":21,"h":19,"orientation":"horizontal"},{"text":"5","x":1460,"y":66,"w":18,"h":22,"orientation":"horizontal"},{"text":"6","x":1749,"y":67,"w":18,"h":21,"orientation":"horizontal"},{"text":"7","x":2037,"y":66,"w":24,"h":22,"orientation":"horizontal"},{"text":"8","x":2326,"y":66,"w":21,"h":21,"orientation":"horizontal"},{"text":"9","x":2617,"y":67,"w":17,"h":20,"orientation":"horizontal"},{"text":"10","x":2897,"y":66,"w":34,"h":21,"orientation":"horizontal"},{"text":"11","x":3188,"y":66,"w":31,"h":21,"orientation":"horizontal"},{"text":"12","x":3474,"y":67,"w":38,"h":21,"orientation":"horizontal"},{"text":"13","x":3763,"y":65,"w":36,"h":23,"orientation":"horizontal"},{"text":"14","x":4052,"y":67,"w":36,"h":20,"orientation":"horizontal"},{"text":"15","x":4340,"y":66,"w":35,"h":22,"orientation":"horizontal"},{"text":"F","x":140,"y":1597,"w":21,"h":24,"orientation":"horizontal"},{"text":"0","x":140,"y":1884,"w":16,"h":24,"orientation":"horizontal"},{"text":"H","x":139,"y":2177,"w":21,"h":21,"orientation":"horizontal"},{"text":"K","x":138,"y":2754,"w":23,"h":23,"orientation":"horizontal"},{"text":"M","x":138,"y":3332,"w":23,"h":22,"orientation":"horizontal"},{"text":"5.5","x":572,"y":386,"w":34,"h":17,"orientation":"horizontal"},{"text":"MATERIALS","x":622,"y":386,"w":110,"h":17,"orientation":"horizontal"},{"text":"HANDLING","x":748,"y":386,"w":102,"h":17,"orientation":"horizontal"},{"text":"5.6","x":1543,"y":386,"w":33,"h":16,"orientation":"horizontal"},{"text":"SEPARATION","x":1590,"y":385,"w":126,"h":18,"orientation":"horizontal"},{"text":"IN","x":1600,"y":529,"w":18,"h":18,"orientation":"horizontal"},{"text":"-","x":1621,"y":529,"w":13,"h":17,"orientation":"horizontal"},{"text":"LINE","x":1638,"y":529,"w":45,"h":17,"orientation":"horizontal"},{"text":"FILTER","x":1698,"y":529,"w":67,"h":17,"orientation":"horizontal"},{"text":"5.0","x":1906,"y":221,"w":67,"h":32,"orientation":"horizontal"},{"text":"MAJOR","x":2005,"y":221,"w":136,"h":32,"orientation":"horizontal"},{"text":"EQUIPMENT","x":2174,"y":221,"w":237,"h":32,"orientation":"horizontal"},{"text":"(","x":1600,"y":552,"w":10,"h":22,"orientation":"horizontal"},{"text":"PFD","x":1610,"y":552,"w":40,"h":22,"orientation":"horizontal"},{"text":"&","x":1664,"y":552,"w":19,"h":22,"orientation":"horizontal"},{"text":"UNDEFINED","x":1698,"y":552,"w":118,"h":22,"orientation":"horizontal"},{"text":"FILTER","x":1830,"y":552,"w":69,"h":22,"orientation":"horizontal"},{"text":")","x":1897,"y":552,"w":11,"h":22,"orientation":"horizontal"},{"text":"IBC","x":768,"y":713,"w":32,"h":21,"orientation":"horizontal"},{"text":"(","x":816,"y":713,"w":8,"h":21,"orientation":"horizontal"},{"text":"SOLIDS","x":826,"y":713,"w":73,"h":22,"orientation":"horizontal"},{"text":")","x":900,"y":713,"w":9,"h":21,"orientation":"horizontal"},{"text":"\u016b","x":1385,"y":684,"w":115,"h":117,"orientation":"horizontal"},{"text":"CARTRIDGE","x":1600,"y":727,"w":113,"h":16,"orientation":"horizontal"},{"text":"FILTER","x":1728,"y":727,"w":69,"h":16,"orientation":"horizontal"},{"text":"IBC","x":825,"y":1522,"w":33,"h":22,"orientation":"horizontal"},{"text":"(","x":874,"y":1522,"w":8,"h":22,"orientation":"horizontal"},{"text":"LIQUIDS","x":885,"y":1522,"w":79,"h":23,"orientation":"horizontal"},{"text":")","x":964,"y":1522,"w":9,"h":22,"orientation":"horizontal"},{"text":"1","x":309,"y":3419,"w":11,"h":21,"orientation":"horizontal"},{"text":"2","x":594,"y":3419,"w":19,"h":21,"orientation":"horizontal"},{"text":"3","x":883,"y":3420,"w":18,"h":19,"orientation":"horizontal"},{"text":"4","x":1170,"y":3420,"w":20,"h":19,"orientation":"horizontal"},{"text":"IN","x":1600,"y":906,"w":18,"h":17,"orientation":"horizontal"},{"text":"-","x":1621,"y":906,"w":13,"h":17,"orientation":"horizontal"},{"text":"LINE","x":1640,"y":906,"w":43,"h":17,"orientation":"horizontal"},{"text":"BASKET","x":1699,"y":906,"w":78,"h":17,"orientation":"horizontal"},{"text":"FILTER","x":1793,"y":906,"w":68,"h":17,"orientation":"horizontal"},{"text":"MESH","x":1600,"y":1062,"w":56,"h":17,"orientation":"horizontal"},{"text":"FILTER","x":1673,"y":1062,"w":68,"h":17,"orientation":"horizontal"},{"text":"(","x":2065,"y":273,"w":10,"h":23,"orientation":"horizontal"},{"text":"NOT","x":2074,"y":273,"w":41,"h":24,"orientation":"horizontal"},{"text":"TO","x":2129,"y":273,"w":26,"h":23,"orientation":"horizontal"},{"text":"SCALE","x":2169,"y":273,"w":67,"h":25,"orientation":"horizontal"},{"text":")","x":2233,"y":275,"w":10,"h":23,"orientation":"horizontal"},{"text":"5.7","x":2470,"y":340,"w":34,"h":16,"orientation":"horizontal"},{"text":"MECHANICAL","x":2520,"y":340,"w":130,"h":16,"orientation":"horizontal"},{"text":"MOVEMENT","x":2665,"y":340,"w":113,"h":16,"orientation":"horizontal"},{"text":"HOIST","x":2594,"y":495,"w":60,"h":17,"orientation":"horizontal"},{"text":"5.8","x":3375,"y":339,"w":34,"h":18,"orientation":"horizontal"},{"text":"MIXING","x":3425,"y":339,"w":70,"h":18,"orientation":"horizontal"},{"text":"EQUIPMENT","x":3511,"y":339,"w":119,"h":18,"orientation":"horizontal"},{"text":"ROTATING","x":3249,"y":631,"w":116,"h":20,"orientation":"horizontal"},{"text":"MIXERS","x":3385,"y":631,"w":91,"h":20,"orientation":"horizontal"},{"text":"H","x":2321,"y":655,"w":12,"h":14,"orientation":"horizontal"},{"text":"HAND","x":2595,"y":692,"w":56,"h":17,"orientation":"horizontal"},{"text":"TRUCK","x":2665,"y":692,"w":70,"h":17,"orientation":"horizontal"},{"text":"OR","x":2750,"y":692,"w":30,"h":17,"orientation":"horizontal"},{"text":"TROLLEY","x":2793,"y":692,"w":91,"h":17,"orientation":"horizontal"},{"text":"WT","x":2332,"y":1241,"w":20,"h":11,"orientation":"horizontal"},{"text":"BAG","x":1601,"y":1276,"w":39,"h":15,"orientation":"horizontal"},{"text":"FILTER","x":1654,"y":1276,"w":70,"h":15,"orientation":"horizontal"},{"text":"5","x":1459,"y":3415,"w":20,"h":29,"orientation":"horizontal"},{"text":"OIL","x":1842,"y":1604,"w":32,"h":20,"orientation":"horizontal"},{"text":"\/","x":1874,"y":1604,"w":13,"h":19,"orientation":"horizontal"},{"text":"WATER","x":1888,"y":1603,"w":68,"h":20,"orientation":"horizontal"},{"text":"SEPARATOR","x":1843,"y":1627,"w":120,"h":18,"orientation":"horizontal"},{"text":"5.9","x":1984,"y":1986,"w":33,"h":17,"orientation":"horizontal"},{"text":"TRANSPORT","x":2032,"y":1985,"w":122,"h":19,"orientation":"horizontal"},{"text":"PEDESTRIAN","x":2595,"y":877,"w":124,"h":16,"orientation":"horizontal"},{"text":"OPERATED","x":2736,"y":877,"w":108,"h":16,"orientation":"horizontal"},{"text":"FORK","x":2594,"y":899,"w":55,"h":17,"orientation":"horizontal"},{"text":"LIFT","x":2665,"y":899,"w":40,"h":17,"orientation":"horizontal"},{"text":"TRUCK","x":2719,"y":899,"w":70,"h":18,"orientation":"horizontal"},{"text":"WEIGH","x":2593,"y":1074,"w":64,"h":16,"orientation":"horizontal"},{"text":"SCALES","x":2673,"y":1074,"w":79,"h":16,"orientation":"horizontal"},{"text":"(","x":2594,"y":1095,"w":9,"h":22,"orientation":"horizontal"},{"text":"LOCAL","x":2604,"y":1095,"w":65,"h":22,"orientation":"horizontal"},{"text":"DIAL","x":2683,"y":1095,"w":45,"h":22,"orientation":"horizontal"},{"text":")","x":2726,"y":1095,"w":10,"h":22,"orientation":"horizontal"},{"text":"WEIGH","x":2593,"y":1282,"w":64,"h":16,"orientation":"horizontal"},{"text":"PLATFORM","x":2674,"y":1282,"w":105,"h":16,"orientation":"horizontal"},{"text":"(","x":2594,"y":1302,"w":10,"h":23,"orientation":"horizontal"},{"text":"LOAD","x":2603,"y":1302,"w":53,"h":23,"orientation":"horizontal"},{"text":"CELLS","x":2671,"y":1302,"w":64,"h":23,"orientation":"horizontal"},{"text":")","x":2735,"y":1303,"w":10,"h":23,"orientation":"horizontal"},{"text":"TRUCK","x":1877,"y":2293,"w":67,"h":16,"orientation":"horizontal"},{"text":"FORK","x":2548,"y":2316,"w":55,"h":17,"orientation":"horizontal"},{"text":"LIFT","x":2619,"y":2316,"w":39,"h":17,"orientation":"horizontal"},{"text":"TRUCK","x":2673,"y":2316,"w":70,"h":17,"orientation":"horizontal"},{"text":"7","x":2039,"y":3419,"w":17,"h":20,"orientation":"horizontal"},{"text":"00","x":2329,"y":3416,"w":15,"h":24,"orientation":"vertical"},{"text":"6","x":2616,"y":3416,"w":16,"h":22,"orientation":"horizontal"},{"text":"STATIC","x":3576,"y":455,"w":67,"h":16,"orientation":"horizontal"},{"text":"MIXER","x":3659,"y":455,"w":62,"h":16,"orientation":"horizontal"},{"text":"PFD's","x":3578,"y":835,"w":59,"h":18,"orientation":"horizontal"},{"text":"&","x":3651,"y":835,"w":16,"h":17,"orientation":"horizontal"},{"text":"UNDEFINED","x":3684,"y":835,"w":117,"h":19,"orientation":"horizontal"},{"text":"FLAT","x":3577,"y":1109,"w":46,"h":15,"orientation":"horizontal"},{"text":"BLADE","x":3639,"y":1109,"w":65,"h":15,"orientation":"horizontal"},{"text":"TUBINE","x":3576,"y":1132,"w":74,"h":16,"orientation":"horizontal"},{"text":"OR","x":3665,"y":1132,"w":30,"h":16,"orientation":"horizontal"},{"text":"PADDLE","x":3710,"y":1132,"w":80,"h":16,"orientation":"horizontal"},{"text":"(","x":3577,"y":1153,"w":9,"h":22,"orientation":"horizontal"},{"text":"RADIAL","x":3587,"y":1153,"w":70,"h":22,"orientation":"horizontal"},{"text":"FLOW","x":3672,"y":1153,"w":53,"h":22,"orientation":"horizontal"},{"text":")","x":3726,"y":1153,"w":10,"h":22,"orientation":"horizontal"},{"text":"INCLINED","x":3577,"y":1409,"w":93,"h":16,"orientation":"horizontal"},{"text":"TURBINE","x":3685,"y":1409,"w":90,"h":16,"orientation":"horizontal"},{"text":"(","x":3577,"y":1430,"w":10,"h":22,"orientation":"horizontal"},{"text":"AXIAL","x":3585,"y":1430,"w":57,"h":22,"orientation":"horizontal"},{"text":"FLOW","x":3656,"y":1430,"w":55,"h":22,"orientation":"horizontal"},{"text":")","x":3711,"y":1430,"w":11,"h":22,"orientation":"horizontal"},{"text":"PROPELLER","x":3577,"y":1710,"w":121,"h":15,"orientation":"horizontal"},{"text":"(","x":3577,"y":1730,"w":10,"h":23,"orientation":"horizontal"},{"text":"AXIAL","x":3583,"y":1729,"w":57,"h":23,"orientation":"horizontal"},{"text":"FLOW","x":3655,"y":1729,"w":55,"h":23,"orientation":"horizontal"},{"text":")","x":3710,"y":1729,"w":10,"h":23,"orientation":"horizontal"},{"text":"DISCIPLINE","x":4299,"y":2026,"w":110,"h":22,"orientation":"horizontal"},{"text":"SIGN","x":4423,"y":2026,"w":48,"h":22,"orientation":"horizontal"},{"text":"-","x":4473,"y":2026,"w":17,"h":22,"orientation":"horizontal"},{"text":"OFF","x":4489,"y":2026,"w":42,"h":22,"orientation":"horizontal"},{"text":"TO","x":3990,"y":2058,"w":16,"h":11,"orientation":"horizontal"},{"text":"SIGN","x":3985,"y":2071,"w":23,"h":13,"orientation":"horizontal"},{"text":"REVISION","x":4033,"y":2061,"w":63,"h":19,"orientation":"horizontal"},{"text":"A","x":4860,"y":154,"w":21,"h":22,"orientation":"horizontal"},{"text":"C","x":4863,"y":734,"w":16,"h":22,"orientation":"vertical"},{"text":"E","x":4862,"y":1309,"w":18,"h":23,"orientation":"horizontal"},{"text":"\u0b9f","x":4861,"y":1597,"w":14,"h":20,"orientation":"horizontal"},{"text":"REV","x":3986,"y":2754,"w":20,"h":11,"orientation":"horizontal"},{"text":".","x":4006,"y":2754,"w":3,"h":11,"orientation":"horizontal"},{"text":"PEM","x":4333,"y":2754,"w":21,"h":11,"orientation":"horizontal"},{"text":"PROJECT","x":4633,"y":2754,"w":48,"h":11,"orientation":"horizontal"},{"text":"CLIENT","x":4719,"y":2754,"w":36,"h":10,"orientation":"horizontal"},{"text":"STATUS","x":4106,"y":2759,"w":38,"h":12,"orientation":"horizontal"},{"text":"DESCRIPTION","x":4168,"y":2759,"w":67,"h":12,"orientation":"horizontal"},{"text":"DRAWN","x":4395,"y":2759,"w":36,"h":11,"orientation":"horizontal"},{"text":"CHECKED","x":4469,"y":2760,"w":51,"h":11,"orientation":"horizontal"},{"text":"APPROVED","x":4547,"y":2760,"w":57,"h":12,"orientation":"horizontal"},{"text":"NO","x":3988,"y":2768,"w":15,"h":11,"orientation":"horizontal"},{"text":".","x":4004,"y":2768,"w":3,"h":11,"orientation":"horizontal"},{"text":"STATUS","x":4324,"y":2768,"w":40,"h":11,"orientation":"horizontal"},{"text":"APPROVAL","x":4629,"y":2768,"w":55,"h":12,"orientation":"horizontal"},{"text":"APPROVAL","x":4710,"y":2768,"w":53,"h":11,"orientation":"horizontal"},{"text":"0","x":4860,"y":1884,"w":17,"h":24,"orientation":"horizontal"},{"text":"H","x":4861,"y":2177,"w":20,"h":21,"orientation":"horizontal"},{"text":"DATE","x":4801,"y":2753,"w":29,"h":22,"orientation":"horizontal"},{"text":"K","x":4859,"y":2753,"w":22,"h":22,"orientation":"horizontal"},{"text":"SCOTTISHPOWER","x":4024,"y":3094,"w":328,"h":28,"orientation":"horizontal"},{"text":"PROJECT","x":3982,"y":3145,"w":92,"h":17,"orientation":"horizontal"},{"text":":","x":4075,"y":3145,"w":6,"h":17,"orientation":"horizontal"},{"text":"TITLE","x":3980,"y":3245,"w":54,"h":28,"orientation":"horizontal"},{"text":":","x":4034,"y":3245,"w":7,"h":27,"orientation":"horizontal"},{"text":"PIPING","x":4057,"y":3245,"w":67,"h":29,"orientation":"horizontal"},{"text":"&","x":4137,"y":3246,"w":16,"h":27,"orientation":"horizontal"},{"text":"INSTRUMENTATION","x":4171,"y":3246,"w":184,"h":30,"orientation":"horizontal"},{"text":"DIAGRAM","x":4370,"y":3249,"w":88,"h":28,"orientation":"horizontal"},{"text":"Aker","x":4553,"y":3038,"w":102,"h":30,"orientation":"horizontal"},{"text":"CleanCarbon","x":4551,"y":3076,"w":263,"h":33,"orientation":"horizontal"},{"text":"\u2122","x":4812,"y":3076,"w":13,"h":33,"orientation":"horizontal"},{"text":"Aker","x":4544,"y":3147,"w":69,"h":23,"orientation":"horizontal"},{"text":"Process","x":4623,"y":3147,"w":114,"h":23,"orientation":"horizontal"},{"text":"Ltd","x":4748,"y":3147,"w":41,"h":23,"orientation":"horizontal"},{"text":"One","x":4545,"y":3182,"w":33,"h":20,"orientation":"horizontal"},{"text":"Port","x":4589,"y":3182,"w":36,"h":20,"orientation":"horizontal"},{"text":"Way","x":4636,"y":3182,"w":35,"h":20,"orientation":"horizontal"},{"text":",","x":4669,"y":3182,"w":6,"h":20,"orientation":"horizontal"},{"text":"Port","x":4687,"y":3182,"w":36,"h":21,"orientation":"horizontal"},{"text":"Solent","x":4733,"y":3183,"w":55,"h":20,"orientation":"horizontal"},{"text":",","x":4787,"y":3183,"w":5,"h":20,"orientation":"horizontal"},{"text":"Portsmouth","x":4497,"y":3206,"w":100,"h":21,"orientation":"horizontal"},{"text":",","x":4597,"y":3206,"w":5,"h":21,"orientation":"horizontal"},{"text":"Hampshire","x":4614,"y":3206,"w":90,"h":21,"orientation":"horizontal"},{"text":",","x":4706,"y":3206,"w":5,"h":21,"orientation":"horizontal"},{"text":"P06","x":4722,"y":3206,"w":34,"h":21,"orientation":"horizontal"},{"text":"4TZ","x":4768,"y":3206,"w":30,"h":21,"orientation":"horizontal"},{"text":",","x":4799,"y":3206,"w":5,"h":21,"orientation":"horizontal"},{"text":"UK","x":4816,"y":3206,"w":24,"h":21,"orientation":"horizontal"},{"text":"LEGEND","x":4057,"y":3285,"w":79,"h":23,"orientation":"horizontal"},{"text":"SHEET","x":4149,"y":3285,"w":66,"h":22,"orientation":"horizontal"},{"text":"EQUIPMENT","x":4057,"y":3319,"w":116,"h":25,"orientation":"horizontal"},{"text":"DETAILS","x":4186,"y":3318,"w":80,"h":25,"orientation":"horizontal"},{"text":"DOCUMENT","x":3981,"y":3356,"w":114,"h":19,"orientation":"horizontal"},{"text":"No","x":4111,"y":3357,"w":27,"h":17,"orientation":"horizontal"},{"text":":","x":4137,"y":3357,"w":7,"h":17,"orientation":"horizontal"},{"text":"SCALE","x":4786,"y":3299,"w":61,"h":17,"orientation":"horizontal"},{"text":"NTS","x":4797,"y":3325,"w":43,"h":23,"orientation":"horizontal"},{"text":"M","x":4858,"y":3330,"w":22,"h":21,"orientation":"horizontal"},{"text":"REV","x":4798,"y":3359,"w":40,"h":14,"orientation":"horizontal"},{"text":"PID","x":4339,"y":3371,"w":33,"h":24,"orientation":"horizontal"},{"text":"-","x":4373,"y":3371,"w":15,"h":24,"orientation":"horizontal"},{"text":"0000","x":4389,"y":3371,"w":54,"h":26,"orientation":"horizontal"},{"text":"Sht4of4","x":4683,"y":3376,"w":83,"h":14,"orientation":"horizontal"},{"text":"A1","x":4831,"y":3420,"w":23,"h":14,"orientation":"horizontal"},{"text":"10","x":2897,"y":3419,"w":33,"h":20,"orientation":"horizontal"},{"text":"11","x":3189,"y":3419,"w":28,"h":22,"orientation":"horizontal"},{"text":"12","x":3474,"y":3419,"w":35,"h":20,"orientation":"horizontal"}]