[{"text":"Back","x":62,"y":23,"w":132,"h":39,"orientation":"horizontal"},{"text":"S","x":199,"y":3206,"w":21,"h":14,"orientation":"vertical"},{"text":":","x":199,"y":3199,"w":21,"h":9,"orientation":"vertical"},{"text":"\\","x":199,"y":3192,"w":21,"h":8,"orientation":"vertical"},{"text":"Gis","x":199,"y":3162,"w":21,"h":31,"orientation":"vertical"},{"text":"\\","x":199,"y":3153,"w":21,"h":10,"orientation":"vertical"},{"text":"Projects","x":199,"y":3076,"w":21,"h":78,"orientation":"vertical"},{"text":"\\","x":199,"y":3067,"w":21,"h":11,"orientation":"vertical"},{"text":"CE","x":199,"y":3039,"w":21,"h":30,"orientation":"vertical"},{"text":"\\","x":199,"y":3031,"w":21,"h":10,"orientation":"vertical"},{"text":"Cenovus","x":199,"y":2948,"w":21,"h":85,"orientation":"vertical"},{"text":"\\","x":199,"y":2939,"w":21,"h":9,"orientation":"vertical"},{"text":"CE0339901_TelephoneLake_EIA","x":199,"y":2618,"w":21,"h":323,"orientation":"vertical"},{"text":"\\","x":199,"y":2610,"w":21,"h":10,"orientation":"vertical"},{"text":"CorelDraw","x":199,"y":2509,"w":21,"h":102,"orientation":"vertical"},{"text":"\\","x":199,"y":2498,"w":21,"h":11,"orientation":"vertical"},{"text":"Application","x":199,"y":2397,"w":21,"h":107,"orientation":"vertical"},{"text":"ReportFigures","x":199,"y":2257,"w":21,"h":137,"orientation":"vertical"},{"text":"\\","x":199,"y":2246,"w":21,"h":11,"orientation":"vertical"},{"text":"Volume","x":199,"y":2178,"w":21,"h":73,"orientation":"vertical"},{"text":"01","x":199,"y":2150,"w":21,"h":21,"orientation":"vertical"},{"text":"Attachment","x":199,"y":2031,"w":21,"h":111,"orientation":"vertical"},{"text":"07","x":199,"y":2001,"w":21,"h":23,"orientation":"vertical"},{"text":"-","x":199,"y":1987,"w":21,"h":8,"orientation":"vertical"},{"text":"Process","x":199,"y":1904,"w":21,"h":76,"orientation":"vertical"},{"text":"Flow","x":199,"y":1851,"w":21,"h":45,"orientation":"vertical"},{"text":"\\","x":199,"y":1842,"w":21,"h":11,"orientation":"vertical"},{"text":"FigATT07-24","x":199,"y":1718,"w":21,"h":127,"orientation":"vertical"},{"text":"\\","x":199,"y":1710,"w":21,"h":9,"orientation":"vertical"},{"text":"FigATT07-24","x":199,"y":1586,"w":21,"h":124,"orientation":"vertical"},{"text":"Sales","x":199,"y":1525,"w":21,"h":54,"orientation":"vertical"},{"text":"Tanks.cdr","x":199,"y":1423,"w":21,"h":95,"orientation":"vertical"},{"text":"OFF","x":279,"y":249,"w":36,"h":15,"orientation":"horizontal"},{"text":"SPEC","x":327,"y":249,"w":51,"h":15,"orientation":"horizontal"},{"text":"OIL","x":391,"y":249,"w":30,"h":15,"orientation":"horizontal"},{"text":"TL1-42","x":328,"y":277,"w":58,"h":15,"orientation":"horizontal"},{"text":"-","x":389,"y":277,"w":9,"h":14,"orientation":"horizontal"},{"text":"PFD","x":401,"y":277,"w":29,"h":14,"orientation":"horizontal"},{"text":"-","x":431,"y":277,"w":10,"h":14,"orientation":"horizontal"},{"text":"04-001-01","x":443,"y":277,"w":95,"h":14,"orientation":"horizontal"},{"text":"FROM","x":280,"y":304,"w":49,"h":15,"orientation":"horizontal"},{"text":"OIL","x":344,"y":304,"w":30,"h":15,"orientation":"horizontal"},{"text":"TREATING","x":387,"y":304,"w":87,"h":15,"orientation":"horizontal"},{"text":"SYSTEM","x":278,"y":323,"w":66,"h":18,"orientation":"horizontal"},{"text":"PHASE","x":383,"y":323,"w":55,"h":18,"orientation":"horizontal"},{"text":"A","x":448,"y":323,"w":13,"h":18,"orientation":"horizontal"},{"text":"\/","x":460,"y":323,"w":12,"h":18,"orientation":"horizontal"},{"text":"B","x":472,"y":323,"w":12,"h":18,"orientation":"horizontal"},{"text":"T","x":911,"y":176,"w":16,"h":22,"orientation":"horizontal"},{"text":"-","x":926,"y":175,"w":15,"h":22,"orientation":"horizontal"},{"text":"6100","x":948,"y":175,"w":64,"h":22,"orientation":"horizontal"},{"text":"\/","x":1015,"y":175,"w":16,"h":22,"orientation":"horizontal"},{"text":"6110","x":1033,"y":174,"w":63,"h":23,"orientation":"horizontal"},{"text":"T","x":1295,"y":175,"w":15,"h":24,"orientation":"horizontal"},{"text":"-","x":1311,"y":174,"w":14,"h":24,"orientation":"horizontal"},{"text":"6200","x":1333,"y":174,"w":64,"h":24,"orientation":"horizontal"},{"text":"\/","x":1399,"y":174,"w":16,"h":24,"orientation":"horizontal"},{"text":"6210","x":1418,"y":174,"w":63,"h":24,"orientation":"horizontal"},{"text":"\/","x":1485,"y":174,"w":16,"h":24,"orientation":"horizontal"},{"text":"6220","x":1501,"y":174,"w":65,"h":24,"orientation":"horizontal"},{"text":"\/","x":1568,"y":173,"w":17,"h":24,"orientation":"horizontal"},{"text":"6230","x":1586,"y":173,"w":65,"h":24,"orientation":"horizontal"},{"text":"SALES","x":890,"y":204,"w":77,"h":19,"orientation":"horizontal"},{"text":"OIL","x":985,"y":204,"w":40,"h":19,"orientation":"horizontal"},{"text":"TANKS","x":1042,"y":204,"w":78,"h":19,"orientation":"horizontal"},{"text":"NOMINAL","x":873,"y":230,"w":82,"h":19,"orientation":"horizontal"},{"text":"CAPACITY","x":967,"y":229,"w":88,"h":19,"orientation":"horizontal"},{"text":":","x":1055,"y":229,"w":6,"h":18,"orientation":"horizontal"},{"text":"9635","x":1075,"y":229,"w":48,"h":18,"orientation":"horizontal"},{"text":"m","x":1137,"y":229,"w":17,"h":18,"orientation":"horizontal"},{"text":"3","x":1158,"y":229,"w":14,"h":18,"orientation":"horizontal"},{"text":"SLOP","x":1365,"y":204,"w":65,"h":19,"orientation":"horizontal"},{"text":"OIL","x":1448,"y":204,"w":40,"h":19,"orientation":"horizontal"},{"text":"TANKS","x":1505,"y":204,"w":79,"h":19,"orientation":"horizontal"},{"text":"NOMINAL","x":1342,"y":228,"w":82,"h":19,"orientation":"horizontal"},{"text":"CAPACITY","x":1438,"y":228,"w":87,"h":19,"orientation":"horizontal"},{"text":":","x":1525,"y":228,"w":5,"h":19,"orientation":"horizontal"},{"text":"801","x":1544,"y":228,"w":36,"h":19,"orientation":"horizontal"},{"text":"m\u00b3","x":1593,"y":228,"w":34,"h":19,"orientation":"horizontal"},{"text":"NNF","x":606,"y":258,"w":37,"h":15,"orientation":"horizontal"},{"text":"SALES","x":279,"y":537,"w":58,"h":14,"orientation":"horizontal"},{"text":"OIL","x":350,"y":537,"w":30,"h":14,"orientation":"horizontal"},{"text":"TL1-42","x":329,"y":564,"w":59,"h":14,"orientation":"horizontal"},{"text":"-","x":389,"y":564,"w":9,"h":14,"orientation":"horizontal"},{"text":"PFD","x":402,"y":564,"w":29,"h":14,"orientation":"horizontal"},{"text":"-","x":432,"y":564,"w":10,"h":14,"orientation":"horizontal"},{"text":"04-001-01","x":444,"y":564,"w":94,"h":14,"orientation":"horizontal"},{"text":"416","x":604,"y":564,"w":30,"h":14,"orientation":"horizontal"},{"text":"FROM","x":280,"y":591,"w":51,"h":15,"orientation":"horizontal"},{"text":"OIL","x":345,"y":591,"w":29,"h":15,"orientation":"horizontal"},{"text":"TREATING","x":387,"y":591,"w":87,"h":15,"orientation":"horizontal"},{"text":"SYSTEM","x":278,"y":610,"w":65,"h":18,"orientation":"horizontal"},{"text":"PHASE","x":383,"y":610,"w":55,"h":18,"orientation":"horizontal"},{"text":"A","x":448,"y":610,"w":13,"h":18,"orientation":"horizontal"},{"text":"\/","x":459,"y":610,"w":12,"h":18,"orientation":"horizontal"},{"text":"B","x":472,"y":610,"w":12,"h":18,"orientation":"horizontal"},{"text":"RECOVERED","x":280,"y":667,"w":111,"h":14,"orientation":"horizontal"},{"text":"SLOP","x":404,"y":667,"w":49,"h":14,"orientation":"horizontal"},{"text":"OIL","x":466,"y":667,"w":31,"h":14,"orientation":"horizontal"},{"text":"TL1-42","x":328,"y":695,"w":59,"h":14,"orientation":"horizontal"},{"text":"-","x":389,"y":695,"w":10,"h":14,"orientation":"horizontal"},{"text":"PFD","x":402,"y":695,"w":29,"h":14,"orientation":"horizontal"},{"text":"-","x":432,"y":695,"w":10,"h":14,"orientation":"horizontal"},{"text":"05-001-01","x":444,"y":695,"w":94,"h":14,"orientation":"horizontal"},{"text":"504","x":604,"y":695,"w":29,"h":13,"orientation":"horizontal"},{"text":"FROM","x":280,"y":721,"w":50,"h":18,"orientation":"horizontal"},{"text":"E","x":345,"y":721,"w":11,"h":18,"orientation":"horizontal"},{"text":"-","x":358,"y":721,"w":13,"h":18,"orientation":"horizontal"},{"text":"5030","x":372,"y":721,"w":50,"h":18,"orientation":"horizontal"},{"text":"A","x":433,"y":721,"w":13,"h":18,"orientation":"horizontal"},{"text":"\/","x":447,"y":721,"w":12,"h":18,"orientation":"horizontal"},{"text":"B","x":461,"y":721,"w":12,"h":18,"orientation":"horizontal"},{"text":",","x":473,"y":721,"w":5,"h":18,"orientation":"horizontal"},{"text":"SLOP","x":492,"y":721,"w":50,"h":18,"orientation":"horizontal"},{"text":"OIL","x":279,"y":740,"w":30,"h":17,"orientation":"horizontal"},{"text":"TREATER","x":321,"y":740,"w":82,"h":17,"orientation":"horizontal"},{"text":"EFFLUENT","x":416,"y":740,"w":93,"h":17,"orientation":"horizontal"},{"text":"\/","x":509,"y":740,"w":12,"h":17,"orientation":"horizontal"},{"text":"GLYCOL","x":279,"y":762,"w":71,"h":16,"orientation":"horizontal"},{"text":"EXCHANGERS","x":364,"y":761,"w":124,"h":17,"orientation":"horizontal"},{"text":"INTD","x":400,"y":1234,"w":37,"h":13,"orientation":"horizontal"},{"text":"04-107-01","x":363,"y":1254,"w":114,"h":14,"orientation":"horizontal"},{"text":"INTD","x":399,"y":1312,"w":39,"h":13,"orientation":"horizontal"},{"text":"04-005-01","x":362,"y":1332,"w":117,"h":15,"orientation":"horizontal"},{"text":"INTD","x":399,"y":1391,"w":39,"h":13,"orientation":"horizontal"},{"text":"04-001-01","x":362,"y":1411,"w":117,"h":14,"orientation":"horizontal"},{"text":"CONDENSED","x":279,"y":1449,"w":116,"h":15,"orientation":"horizontal"},{"text":"LIQUIDS","x":408,"y":1449,"w":72,"h":15,"orientation":"horizontal"},{"text":"TL1-42","x":328,"y":1476,"w":59,"h":15,"orientation":"horizontal"},{"text":"-","x":389,"y":1476,"w":9,"h":15,"orientation":"horizontal"},{"text":"PFD","x":402,"y":1476,"w":29,"h":15,"orientation":"horizontal"},{"text":"-","x":433,"y":1476,"w":10,"h":15,"orientation":"horizontal"},{"text":"07-001-01","x":443,"y":1476,"w":94,"h":15,"orientation":"horizontal"},{"text":"FROM","x":279,"y":1503,"w":51,"h":19,"orientation":"horizontal"},{"text":"V","x":343,"y":1503,"w":14,"h":19,"orientation":"horizontal"},{"text":"-","x":357,"y":1503,"w":13,"h":19,"orientation":"horizontal"},{"text":"7600","x":372,"y":1503,"w":50,"h":19,"orientation":"horizontal"},{"text":"\/","x":421,"y":1503,"w":13,"h":19,"orientation":"horizontal"},{"text":"7610","x":436,"y":1503,"w":49,"h":19,"orientation":"horizontal"},{"text":"\/","x":485,"y":1503,"w":13,"h":19,"orientation":"horizontal"},{"text":"7620","x":498,"y":1503,"w":50,"h":19,"orientation":"horizontal"},{"text":"\/","x":548,"y":1503,"w":14,"h":19,"orientation":"horizontal"},{"text":"7630","x":279,"y":1521,"w":49,"h":17,"orientation":"horizontal"},{"text":",","x":329,"y":1521,"w":4,"h":17,"orientation":"horizontal"},{"text":"EJECTOR","x":348,"y":1521,"w":83,"h":17,"orientation":"horizontal"},{"text":"SUCTION","x":444,"y":1521,"w":79,"h":17,"orientation":"horizontal"},{"text":"SCRUBBER","x":538,"y":1521,"w":104,"h":17,"orientation":"horizontal"},{"text":"PRODUCED","x":280,"y":1579,"w":103,"h":14,"orientation":"horizontal"},{"text":"WATER","x":395,"y":1579,"w":62,"h":14,"orientation":"horizontal"},{"text":"TL1-42","x":329,"y":1607,"w":59,"h":14,"orientation":"horizontal"},{"text":"-","x":389,"y":1607,"w":9,"h":14,"orientation":"horizontal"},{"text":"PFD","x":402,"y":1607,"w":29,"h":14,"orientation":"horizontal"},{"text":"-","x":432,"y":1607,"w":10,"h":14,"orientation":"horizontal"},{"text":"07-002-01","x":443,"y":1607,"w":95,"h":14,"orientation":"horizontal"},{"text":"FROM","x":279,"y":1634,"w":51,"h":15,"orientation":"horizontal"},{"text":"V","x":343,"y":1634,"w":13,"h":15,"orientation":"horizontal"},{"text":"-","x":357,"y":1634,"w":13,"h":15,"orientation":"horizontal"},{"text":"7020","x":372,"y":1634,"w":49,"h":15,"orientation":"horizontal"},{"text":",","x":421,"y":1634,"w":5,"h":15,"orientation":"horizontal"},{"text":"FUEL","x":441,"y":1634,"w":48,"h":15,"orientation":"horizontal"},{"text":"GAS","x":501,"y":1634,"w":36,"h":15,"orientation":"horizontal"},{"text":"MIX","x":280,"y":1654,"w":31,"h":13,"orientation":"horizontal"},{"text":"DRUM","x":325,"y":1654,"w":52,"h":13,"orientation":"horizontal"},{"text":"PRODUCED","x":279,"y":1710,"w":104,"h":14,"orientation":"horizontal"},{"text":"WATER","x":395,"y":1710,"w":62,"h":14,"orientation":"horizontal"},{"text":"TL1-42","x":328,"y":1737,"w":59,"h":15,"orientation":"horizontal"},{"text":"-","x":389,"y":1737,"w":10,"h":15,"orientation":"horizontal"},{"text":"PFD","x":402,"y":1737,"w":29,"h":15,"orientation":"horizontal"},{"text":"-","x":432,"y":1737,"w":10,"h":15,"orientation":"horizontal"},{"text":"04-003-01","x":444,"y":1737,"w":94,"h":15,"orientation":"horizontal"},{"text":"FROM","x":279,"y":1764,"w":51,"h":18,"orientation":"horizontal"},{"text":"P","x":345,"y":1764,"w":12,"h":18,"orientation":"horizontal"},{"text":"-","x":358,"y":1764,"w":13,"h":18,"orientation":"horizontal"},{"text":"4085","x":374,"y":1764,"w":48,"h":18,"orientation":"horizontal"},{"text":"A","x":436,"y":1764,"w":13,"h":18,"orientation":"horizontal"},{"text":"\/","x":448,"y":1764,"w":12,"h":18,"orientation":"horizontal"},{"text":"B","x":462,"y":1764,"w":11,"h":18,"orientation":"horizontal"},{"text":",","x":475,"y":1764,"w":5,"h":18,"orientation":"horizontal"},{"text":"DESAND","x":495,"y":1764,"w":73,"h":18,"orientation":"horizontal"},{"text":"TANK","x":279,"y":1783,"w":47,"h":16,"orientation":"horizontal"},{"text":"DECANT","x":341,"y":1783,"w":72,"h":16,"orientation":"horizontal"},{"text":"PUMPS","x":426,"y":1783,"w":66,"h":16,"orientation":"horizontal"},{"text":"LIQUIDS","x":280,"y":1840,"w":70,"h":15,"orientation":"horizontal"},{"text":"TL1-42","x":329,"y":1868,"w":59,"h":14,"orientation":"horizontal"},{"text":"-","x":389,"y":1868,"w":10,"h":14,"orientation":"horizontal"},{"text":"PFD","x":402,"y":1868,"w":29,"h":14,"orientation":"horizontal"},{"text":"-","x":432,"y":1868,"w":10,"h":14,"orientation":"horizontal"},{"text":"07-005-01","x":443,"y":1868,"w":94,"h":14,"orientation":"horizontal"},{"text":"FROM","x":280,"y":1894,"w":49,"h":16,"orientation":"horizontal"},{"text":"P","x":346,"y":1894,"w":11,"h":16,"orientation":"horizontal"},{"text":"-","x":359,"y":1894,"w":12,"h":16,"orientation":"horizontal"},{"text":"7505","x":375,"y":1894,"w":47,"h":16,"orientation":"horizontal"},{"text":"A","x":435,"y":1894,"w":14,"h":16,"orientation":"horizontal"},{"text":"\/","x":449,"y":1894,"w":13,"h":16,"orientation":"horizontal"},{"text":"B","x":462,"y":1894,"w":12,"h":16,"orientation":"horizontal"},{"text":",","x":475,"y":1894,"w":4,"h":16,"orientation":"horizontal"},{"text":"FLARE","x":494,"y":1894,"w":57,"h":17,"orientation":"horizontal"},{"text":"KNOCK","x":279,"y":1913,"w":64,"h":16,"orientation":"horizontal"},{"text":"-","x":346,"y":1913,"w":12,"h":16,"orientation":"horizontal"},{"text":"OUT","x":362,"y":1913,"w":37,"h":16,"orientation":"horizontal"},{"text":"DRUM","x":412,"y":1913,"w":53,"h":16,"orientation":"horizontal"},{"text":"PUMPS","x":480,"y":1913,"w":66,"h":16,"orientation":"horizontal"},{"text":"PRODUCED","x":280,"y":1971,"w":102,"h":14,"orientation":"horizontal"},{"text":"GAS","x":397,"y":1971,"w":36,"h":14,"orientation":"horizontal"},{"text":"LIQUIDS","x":447,"y":1971,"w":71,"h":14,"orientation":"horizontal"},{"text":"TL1-42","x":328,"y":1999,"w":59,"h":14,"orientation":"horizontal"},{"text":"-","x":389,"y":1999,"w":10,"h":14,"orientation":"horizontal"},{"text":"PFD","x":402,"y":1999,"w":29,"h":14,"orientation":"horizontal"},{"text":"-","x":432,"y":1999,"w":10,"h":14,"orientation":"horizontal"},{"text":"04-002-01","x":444,"y":1999,"w":94,"h":14,"orientation":"horizontal"},{"text":"FROM","x":280,"y":2025,"w":50,"h":16,"orientation":"horizontal"},{"text":"V","x":343,"y":2025,"w":13,"h":16,"orientation":"horizontal"},{"text":"-","x":357,"y":2025,"w":12,"h":16,"orientation":"horizontal"},{"text":"4055","x":371,"y":2025,"w":50,"h":16,"orientation":"horizontal"},{"text":",","x":422,"y":2025,"w":4,"h":16,"orientation":"horizontal"},{"text":"PRODUCED","x":442,"y":2025,"w":104,"h":16,"orientation":"horizontal"},{"text":"GAS","x":279,"y":2047,"w":37,"h":15,"orientation":"horizontal"},{"text":"KNOCK","x":329,"y":2047,"w":65,"h":15,"orientation":"horizontal"},{"text":"OUT","x":408,"y":2047,"w":38,"h":15,"orientation":"horizontal"},{"text":"DRUM","x":458,"y":2047,"w":54,"h":15,"orientation":"horizontal"},{"text":"NNF","x":606,"y":1588,"w":36,"h":14,"orientation":"horizontal"},{"text":"TH","x":638,"y":383,"w":15,"h":14,"orientation":"horizontal"},{"text":"OFF","x":969,"y":365,"w":36,"h":15,"orientation":"horizontal"},{"text":"-","x":1007,"y":365,"w":12,"h":15,"orientation":"horizontal"},{"text":"SPEC","x":1020,"y":365,"w":51,"h":15,"orientation":"horizontal"},{"text":"HEADER","x":1085,"y":365,"w":74,"h":15,"orientation":"horizontal"},{"text":"SALES","x":970,"y":441,"w":59,"h":15,"orientation":"horizontal"},{"text":"OIL","x":1042,"y":441,"w":29,"h":15,"orientation":"horizontal"},{"text":"HEADER","x":1085,"y":441,"w":73,"h":15,"orientation":"horizontal"},{"text":"TH","x":639,"y":461,"w":12,"h":13,"orientation":"horizontal"},{"text":"777","x":642,"y":1476,"w":29,"h":14,"orientation":"horizontal"},{"text":"LLP","x":953,"y":842,"w":32,"h":14,"orientation":"horizontal"},{"text":"BG","x":999,"y":842,"w":26,"h":14,"orientation":"horizontal"},{"text":"07-002-01","x":931,"y":862,"w":117,"h":16,"orientation":"horizontal"},{"text":"HGL","x":935,"y":1234,"w":35,"h":13,"orientation":"horizontal"},{"text":"07-003-01","x":896,"y":1254,"w":117,"h":14,"orientation":"horizontal"},{"text":"TC","x":1013,"y":1100,"w":19,"h":14,"orientation":"horizontal"},{"text":"2","x":1091,"y":826,"w":43,"h":39,"orientation":"horizontal"},{"text":".","x":1116,"y":826,"w":27,"h":39,"orientation":"horizontal"},{"text":"607","x":1216,"y":865,"w":29,"h":13,"orientation":"horizontal"},{"text":"T","x":1126,"y":978,"w":14,"h":18,"orientation":"horizontal"},{"text":"-","x":1141,"y":978,"w":15,"h":18,"orientation":"horizontal"},{"text":"6100","x":1163,"y":978,"w":63,"h":18,"orientation":"horizontal"},{"text":"NNF","x":612,"y":1719,"w":39,"h":14,"orientation":"horizontal"},{"text":"LLP","x":918,"y":1768,"w":32,"h":14,"orientation":"horizontal"},{"text":"BG","x":965,"y":1768,"w":26,"h":14,"orientation":"horizontal"},{"text":"07-002-01","x":896,"y":1789,"w":116,"h":15,"orientation":"horizontal"},{"text":"612","x":1216,"y":1798,"w":28,"h":14,"orientation":"horizontal"},{"text":"NNF","x":606,"y":1850,"w":38,"h":14,"orientation":"horizontal"},{"text":"\u601d","x":919,"y":1879,"w":53,"h":43,"orientation":"horizontal"},{"text":"TC","x":1105,"y":1961,"w":19,"h":13,"orientation":"horizontal"},{"text":"425","x":642,"y":1999,"w":28,"h":12,"orientation":"horizontal"},{"text":"PRODUCED","x":279,"y":2101,"w":104,"h":15,"orientation":"horizontal"},{"text":"GAS","x":396,"y":2101,"w":36,"h":15,"orientation":"horizontal"},{"text":"LIQUIDS","x":447,"y":2101,"w":71,"h":15,"orientation":"horizontal"},{"text":"TL1-42","x":329,"y":2128,"w":58,"h":16,"orientation":"horizontal"},{"text":"-","x":388,"y":2128,"w":10,"h":15,"orientation":"horizontal"},{"text":"PFD","x":401,"y":2128,"w":30,"h":15,"orientation":"horizontal"},{"text":"-","x":431,"y":2128,"w":10,"h":15,"orientation":"horizontal"},{"text":"04-002-01","x":443,"y":2128,"w":95,"h":15,"orientation":"horizontal"},{"text":"423","x":642,"y":2129,"w":30,"h":14,"orientation":"horizontal"},{"text":"FROM","x":280,"y":2156,"w":50,"h":15,"orientation":"horizontal"},{"text":"V","x":343,"y":2156,"w":13,"h":15,"orientation":"horizontal"},{"text":"-","x":357,"y":2156,"w":11,"h":15,"orientation":"horizontal"},{"text":"4030","x":372,"y":2156,"w":49,"h":15,"orientation":"horizontal"},{"text":",","x":422,"y":2156,"w":5,"h":15,"orientation":"horizontal"},{"text":"PG","x":441,"y":2156,"w":26,"h":15,"orientation":"horizontal"},{"text":"HGL","x":935,"y":2159,"w":37,"h":15,"orientation":"horizontal"},{"text":"07-003-01","x":897,"y":2178,"w":115,"h":16,"orientation":"horizontal"},{"text":"SLUG","x":279,"y":2177,"w":49,"h":14,"orientation":"horizontal"},{"text":"CATCHER","x":342,"y":2177,"w":86,"h":14,"orientation":"horizontal"},{"text":"PRODUCED","x":279,"y":2227,"w":103,"h":15,"orientation":"horizontal"},{"text":"WATER","x":394,"y":2227,"w":63,"h":15,"orientation":"horizontal"},{"text":"NNF","x":606,"y":2237,"w":38,"h":13,"orientation":"horizontal"},{"text":"TL1-42","x":328,"y":2254,"w":60,"h":15,"orientation":"horizontal"},{"text":"-","x":389,"y":2254,"w":10,"h":15,"orientation":"horizontal"},{"text":"PFD","x":402,"y":2254,"w":29,"h":15,"orientation":"horizontal"},{"text":"-","x":433,"y":2254,"w":10,"h":15,"orientation":"horizontal"},{"text":"08-003-01","x":443,"y":2254,"w":95,"h":15,"orientation":"horizontal"},{"text":"FROM","x":279,"y":2282,"w":51,"h":14,"orientation":"horizontal"},{"text":"V","x":343,"y":2282,"w":13,"h":14,"orientation":"horizontal"},{"text":"-","x":357,"y":2282,"w":11,"h":14,"orientation":"horizontal"},{"text":"8500","x":372,"y":2282,"w":49,"h":14,"orientation":"horizontal"},{"text":"SCAVENGER","x":279,"y":2303,"w":111,"h":15,"orientation":"horizontal"},{"text":"INLET","x":404,"y":2303,"w":50,"h":15,"orientation":"horizontal"},{"text":"SEPARATOR","x":467,"y":2303,"w":109,"h":15,"orientation":"horizontal"},{"text":"TH","x":638,"y":2338,"w":15,"h":14,"orientation":"horizontal"},{"text":"RECYCLED","x":280,"y":2388,"w":95,"h":15,"orientation":"horizontal"},{"text":"SLOP","x":389,"y":2388,"w":50,"h":15,"orientation":"horizontal"},{"text":"OIL","x":452,"y":2388,"w":30,"h":15,"orientation":"horizontal"},{"text":"TL1-42","x":328,"y":2415,"w":59,"h":15,"orientation":"horizontal"},{"text":"-","x":389,"y":2415,"w":10,"h":15,"orientation":"horizontal"},{"text":"PFD","x":402,"y":2415,"w":29,"h":15,"orientation":"horizontal"},{"text":"-","x":432,"y":2415,"w":10,"h":15,"orientation":"horizontal"},{"text":"01-001-01","x":444,"y":2415,"w":94,"h":15,"orientation":"horizontal"},{"text":"104","x":616,"y":2415,"w":27,"h":14,"orientation":"horizontal"},{"text":"FROM","x":279,"y":2442,"w":50,"h":17,"orientation":"horizontal"},{"text":"P","x":345,"y":2442,"w":11,"h":17,"orientation":"horizontal"},{"text":"-","x":358,"y":2442,"w":13,"h":17,"orientation":"horizontal"},{"text":"1155","x":375,"y":2442,"w":48,"h":17,"orientation":"horizontal"},{"text":"A","x":435,"y":2442,"w":14,"h":17,"orientation":"horizontal"},{"text":"\/","x":448,"y":2442,"w":12,"h":17,"orientation":"horizontal"},{"text":"B","x":462,"y":2442,"w":12,"h":17,"orientation":"horizontal"},{"text":",","x":475,"y":2442,"w":6,"h":17,"orientation":"horizontal"},{"text":"OIL","x":494,"y":2442,"w":29,"h":17,"orientation":"horizontal"},{"text":"RECYCLE","x":280,"y":2462,"w":82,"h":14,"orientation":"horizontal"},{"text":"PUMPS","x":377,"y":2462,"w":66,"h":14,"orientation":"horizontal"},{"text":"RECYCLED","x":280,"y":2518,"w":95,"h":14,"orientation":"horizontal"},{"text":"SLOP","x":389,"y":2518,"w":50,"h":14,"orientation":"horizontal"},{"text":"OIL","x":452,"y":2518,"w":30,"h":14,"orientation":"horizontal"},{"text":"TL1-42","x":329,"y":2545,"w":58,"h":15,"orientation":"horizontal"},{"text":"-","x":389,"y":2545,"w":10,"h":15,"orientation":"horizontal"},{"text":"PFD","x":402,"y":2545,"w":30,"h":15,"orientation":"horizontal"},{"text":"-","x":432,"y":2545,"w":11,"h":15,"orientation":"horizontal"},{"text":"01-005-01","x":443,"y":2545,"w":94,"h":15,"orientation":"horizontal"},{"text":"154","x":616,"y":2545,"w":29,"h":14,"orientation":"horizontal"},{"text":"FROM","x":279,"y":2573,"w":51,"h":17,"orientation":"horizontal"},{"text":"P","x":345,"y":2573,"w":12,"h":17,"orientation":"horizontal"},{"text":"-","x":359,"y":2573,"w":12,"h":17,"orientation":"horizontal"},{"text":"1455","x":375,"y":2573,"w":48,"h":17,"orientation":"horizontal"},{"text":"A","x":435,"y":2573,"w":13,"h":17,"orientation":"horizontal"},{"text":"\/","x":448,"y":2573,"w":12,"h":17,"orientation":"horizontal"},{"text":"B","x":462,"y":2573,"w":12,"h":17,"orientation":"horizontal"},{"text":",","x":474,"y":2573,"w":6,"h":17,"orientation":"horizontal"},{"text":"OIL","x":493,"y":2573,"w":30,"h":17,"orientation":"horizontal"},{"text":"RECYCLE","x":279,"y":2592,"w":84,"h":15,"orientation":"horizontal"},{"text":"PUMPS","x":377,"y":2592,"w":66,"h":15,"orientation":"horizontal"},{"text":"||","x":770,"y":2703,"w":7,"h":14,"orientation":"horizontal"},{"text":"NOTES","x":281,"y":2802,"w":78,"h":21,"orientation":"horizontal"},{"text":":","x":363,"y":2803,"w":6,"h":19,"orientation":"horizontal"},{"text":"1.","x":281,"y":2834,"w":16,"h":16,"orientation":"horizontal"},{"text":"ALL","x":310,"y":2834,"w":34,"h":16,"orientation":"horizontal"},{"text":"EQUIPMENT","x":358,"y":2834,"w":105,"h":16,"orientation":"horizontal"},{"text":"SHOWN","x":477,"y":2834,"w":66,"h":16,"orientation":"horizontal"},{"text":"IS","x":559,"y":2834,"w":16,"h":16,"orientation":"horizontal"},{"text":"PHASE","x":590,"y":2834,"w":61,"h":16,"orientation":"horizontal"},{"text":"A","x":663,"y":2834,"w":12,"h":16,"orientation":"horizontal"},{"text":",","x":676,"y":2834,"w":4,"h":16,"orientation":"horizontal"},{"text":"EXCEPT","x":694,"y":2834,"w":73,"h":16,"orientation":"horizontal"},{"text":"WHERE","x":778,"y":2834,"w":67,"h":16,"orientation":"horizontal"},{"text":"NOTED","x":858,"y":2834,"w":61,"h":16,"orientation":"horizontal"},{"text":".","x":919,"y":2834,"w":5,"h":16,"orientation":"horizontal"},{"text":"2.","x":279,"y":2853,"w":18,"h":15,"orientation":"horizontal"},{"text":"ALL","x":310,"y":2853,"w":34,"h":15,"orientation":"horizontal"},{"text":"TAG","x":357,"y":2853,"w":33,"h":15,"orientation":"horizontal"},{"text":"NUMBERS","x":404,"y":2853,"w":92,"h":15,"orientation":"horizontal"},{"text":"TO","x":509,"y":2853,"w":22,"h":15,"orientation":"horizontal"},{"text":"BE","x":548,"y":2853,"w":22,"h":15,"orientation":"horizontal"},{"text":"PREFIXED","x":584,"y":2853,"w":91,"h":15,"orientation":"horizontal"},{"text":"BY","x":689,"y":2853,"w":24,"h":15,"orientation":"horizontal"},{"text":"\"","x":725,"y":2853,"w":8,"h":15,"orientation":"horizontal"},{"text":"TL1-","x":734,"y":2853,"w":46,"h":15,"orientation":"horizontal"},{"text":"\"","x":783,"y":2853,"w":9,"h":15,"orientation":"horizontal"},{"text":".","x":792,"y":2853,"w":4,"h":15,"orientation":"horizontal"},{"text":"3.","x":279,"y":2871,"w":18,"h":21,"orientation":"horizontal"},{"text":"P","x":311,"y":2871,"w":12,"h":21,"orientation":"horizontal"},{"text":"-","x":326,"y":2871,"w":13,"h":21,"orientation":"horizontal"},{"text":"6150","x":340,"y":2871,"w":50,"h":21,"orientation":"horizontal"},{"text":"A","x":400,"y":2871,"w":15,"h":21,"orientation":"horizontal"},{"text":"\/","x":414,"y":2871,"w":14,"h":21,"orientation":"horizontal"},{"text":"B","x":429,"y":2871,"w":12,"h":21,"orientation":"horizontal"},{"text":"FOR","x":455,"y":2871,"w":36,"h":21,"orientation":"horizontal"},{"text":"PHASE","x":505,"y":2871,"w":61,"h":21,"orientation":"horizontal"},{"text":"A","x":578,"y":2871,"w":13,"h":21,"orientation":"horizontal"},{"text":"AND","x":602,"y":2871,"w":40,"h":21,"orientation":"horizontal"},{"text":"P","x":656,"y":2871,"w":11,"h":21,"orientation":"horizontal"},{"text":"-","x":669,"y":2871,"w":13,"h":21,"orientation":"horizontal"},{"text":"6150C","x":684,"y":2871,"w":62,"h":21,"orientation":"horizontal"},{"text":"FOR","x":760,"y":2871,"w":39,"h":21,"orientation":"horizontal"},{"text":"PHASE","x":812,"y":2871,"w":62,"h":21,"orientation":"horizontal"},{"text":"B","x":886,"y":2871,"w":11,"h":21,"orientation":"horizontal"},{"text":"(","x":913,"y":2871,"w":7,"h":21,"orientation":"horizontal"},{"text":"HOLD","x":921,"y":2871,"w":51,"h":21,"orientation":"horizontal"},{"text":")","x":971,"y":2871,"w":9,"h":21,"orientation":"horizontal"},{"text":".","x":981,"y":2871,"w":4,"h":21,"orientation":"horizontal"},{"text":"4.","x":279,"y":2892,"w":18,"h":15,"orientation":"horizontal"},{"text":"DELETED","x":312,"y":2891,"w":79,"h":17,"orientation":"horizontal"},{"text":".","x":394,"y":2893,"w":4,"h":15,"orientation":"horizontal"},{"text":"5.","x":279,"y":2912,"w":19,"h":15,"orientation":"horizontal"},{"text":"PRODUCED","x":312,"y":2912,"w":103,"h":15,"orientation":"horizontal"},{"text":"WATER","x":428,"y":2912,"w":61,"h":15,"orientation":"horizontal"},{"text":"FROM","x":504,"y":2912,"w":50,"h":15,"orientation":"horizontal"},{"text":"SRF","x":569,"y":2912,"w":36,"h":15,"orientation":"horizontal"},{"text":"ACCORDING","x":617,"y":2912,"w":109,"h":15,"orientation":"horizontal"},{"text":"TO","x":740,"y":2912,"w":22,"h":15,"orientation":"horizontal"},{"text":"DESIGN","x":777,"y":2912,"w":66,"h":15,"orientation":"horizontal"},{"text":"CASE","x":858,"y":2912,"w":49,"h":15,"orientation":"horizontal"},{"text":".","x":908,"y":2912,"w":5,"h":15,"orientation":"horizontal"},{"text":"Source","x":259,"y":3183,"w":65,"h":18,"orientation":"horizontal"},{"text":":","x":325,"y":3183,"w":6,"h":18,"orientation":"horizontal"},{"text":"Cenovus","x":336,"y":3183,"w":81,"h":18,"orientation":"horizontal"},{"text":",","x":419,"y":3183,"w":4,"h":18,"orientation":"horizontal"},{"text":"Tri","x":430,"y":3183,"w":22,"h":18,"orientation":"horizontal"},{"text":"Ocean","x":458,"y":3184,"w":60,"h":18,"orientation":"horizontal"},{"text":"Engineering","x":525,"y":3183,"w":110,"h":20,"orientation":"horizontal"},{"text":".","x":636,"y":3184,"w":5,"h":18,"orientation":"horizontal"},{"text":"T","x":1126,"y":1903,"w":14,"h":19,"orientation":"horizontal"},{"text":"-","x":1141,"y":1902,"w":13,"h":19,"orientation":"horizontal"},{"text":"6200","x":1163,"y":1902,"w":62,"h":19,"orientation":"horizontal"},{"text":"TRUCK","x":1022,"y":2242,"w":61,"h":15,"orientation":"horizontal"},{"text":"-","x":1085,"y":2242,"w":13,"h":15,"orientation":"horizontal"},{"text":"OUT","x":1101,"y":2242,"w":37,"h":15,"orientation":"horizontal"},{"text":"HEADER","x":1152,"y":2242,"w":73,"h":15,"orientation":"horizontal"},{"text":"SLOP","x":1022,"y":2321,"w":49,"h":15,"orientation":"horizontal"},{"text":"OIL","x":1084,"y":2321,"w":31,"h":15,"orientation":"horizontal"},{"text":"INLET","x":1127,"y":2321,"w":52,"h":15,"orientation":"horizontal"},{"text":"HEADER","x":1191,"y":2321,"w":75,"h":15,"orientation":"horizontal"},{"text":"RECYCLED","x":1023,"y":2399,"w":95,"h":14,"orientation":"horizontal"},{"text":"SLOP","x":1132,"y":2399,"w":50,"h":14,"orientation":"horizontal"},{"text":"OIL","x":1195,"y":2399,"w":31,"h":14,"orientation":"horizontal"},{"text":"TH","x":1277,"y":1452,"w":14,"h":13,"orientation":"horizontal"},{"text":"TH","x":1277,"y":1529,"w":13,"h":15,"orientation":"horizontal"},{"text":"TH","x":1277,"y":1608,"w":12,"h":15,"orientation":"horizontal"},{"text":"VG","x":1352,"y":791,"w":27,"h":14,"orientation":"horizontal"},{"text":"07-001-01","x":1307,"y":812,"w":116,"h":14,"orientation":"horizontal"},{"text":"\u2611","x":1353,"y":1179,"w":17,"h":31,"orientation":"vertical"},{"text":"VG","x":1352,"y":1732,"w":26,"h":14,"orientation":"horizontal"},{"text":"\u2611X","x":1372,"y":1006,"w":29,"h":40,"orientation":"horizontal"},{"text":"07-001-01","x":1307,"y":1750,"w":116,"h":18,"orientation":"horizontal"},{"text":"888","x":1456,"y":1870,"w":71,"h":34,"orientation":"horizontal"},{"text":"RECYCLED","x":1023,"y":2528,"w":96,"h":18,"orientation":"horizontal"},{"text":"OFF","x":1132,"y":2528,"w":37,"h":18,"orientation":"horizontal"},{"text":"-","x":1170,"y":2528,"w":13,"h":18,"orientation":"horizontal"},{"text":"SPEC","x":1185,"y":2528,"w":49,"h":18,"orientation":"horizontal"},{"text":"\/","x":1235,"y":2528,"w":14,"h":18,"orientation":"horizontal"},{"text":"TANK","x":1248,"y":2528,"w":48,"h":18,"orientation":"horizontal"},{"text":"HEATING","x":1310,"y":2528,"w":77,"h":18,"orientation":"horizontal"},{"text":"HEADER","x":1401,"y":2528,"w":75,"h":18,"orientation":"horizontal"},{"text":"RECYCLED","x":1023,"y":2686,"w":95,"h":14,"orientation":"horizontal"},{"text":"EMULSION","x":1133,"y":2686,"w":94,"h":14,"orientation":"horizontal"},{"text":"LLP","x":1661,"y":842,"w":31,"h":14,"orientation":"horizontal"},{"text":"BG","x":1709,"y":842,"w":24,"h":14,"orientation":"horizontal"},{"text":"07-002-01","x":1640,"y":863,"w":115,"h":15,"orientation":"horizontal"},{"text":"HGL","x":1679,"y":1234,"w":35,"h":13,"orientation":"horizontal"},{"text":"07-003-01","x":1639,"y":1254,"w":115,"h":14,"orientation":"horizontal"},{"text":"TC","x":1757,"y":1100,"w":17,"h":14,"orientation":"horizontal"},{"text":"\u2611D","x":1750,"y":1153,"w":30,"h":56,"orientation":"vertical"},{"text":"SALES","x":1590,"y":1367,"w":58,"h":14,"orientation":"horizontal"},{"text":"OIL","x":1661,"y":1367,"w":29,"h":14,"orientation":"horizontal"},{"text":"HEADER","x":1704,"y":1367,"w":73,"h":14,"orientation":"horizontal"},{"text":"Main","x":1808,"y":21,"w":98,"h":45,"orientation":"horizontal"},{"text":"Menu","x":1925,"y":21,"w":112,"h":45,"orientation":"horizontal"},{"text":"Search","x":2078,"y":21,"w":187,"h":45,"orientation":"horizontal"},{"text":"Main","x":2308,"y":21,"w":106,"h":45,"orientation":"horizontal"},{"text":"TOC","x":2433,"y":21,"w":105,"h":45,"orientation":"horizontal"},{"text":"P","x":1847,"y":174,"w":16,"h":22,"orientation":"horizontal"},{"text":"-","x":1866,"y":174,"w":15,"h":22,"orientation":"horizontal"},{"text":"6150","x":1887,"y":174,"w":65,"h":22,"orientation":"horizontal"},{"text":"A","x":1967,"y":174,"w":18,"h":22,"orientation":"horizontal"},{"text":"\/","x":1986,"y":174,"w":15,"h":22,"orientation":"horizontal"},{"text":"B","x":2002,"y":174,"w":15,"h":22,"orientation":"horizontal"},{"text":"\/","x":2020,"y":174,"w":17,"h":22,"orientation":"horizontal"},{"text":"C","x":2036,"y":175,"w":19,"h":22,"orientation":"horizontal"},{"text":"LACT","x":1802,"y":204,"w":58,"h":19,"orientation":"horizontal"},{"text":"BOOSTER","x":1879,"y":204,"w":115,"h":19,"orientation":"horizontal"},{"text":"PUMPS","x":2013,"y":204,"w":89,"h":19,"orientation":"horizontal"},{"text":"RATED","x":1818,"y":228,"w":58,"h":21,"orientation":"horizontal"},{"text":"FLOW","x":1890,"y":228,"w":49,"h":21,"orientation":"horizontal"},{"text":":","x":1940,"y":228,"w":6,"h":21,"orientation":"horizontal"},{"text":"493","x":1959,"y":228,"w":37,"h":21,"orientation":"horizontal"},{"text":"Am","x":2007,"y":228,"w":31,"h":21,"orientation":"horizontal"},{"text":"\u00b3","x":2045,"y":228,"w":15,"h":21,"orientation":"horizontal"},{"text":"\/","x":2053,"y":228,"w":13,"h":21,"orientation":"horizontal"},{"text":"h","x":2066,"y":228,"w":12,"h":21,"orientation":"horizontal"},{"text":"P","x":2223,"y":174,"w":16,"h":23,"orientation":"horizontal"},{"text":"-","x":2242,"y":174,"w":16,"h":23,"orientation":"horizontal"},{"text":"6250","x":2263,"y":174,"w":64,"h":23,"orientation":"horizontal"},{"text":"A","x":2344,"y":174,"w":18,"h":23,"orientation":"horizontal"},{"text":"\/","x":2361,"y":174,"w":18,"h":23,"orientation":"horizontal"},{"text":"B","x":2379,"y":175,"w":17,"h":23,"orientation":"horizontal"},{"text":"SLOP","x":2158,"y":204,"w":65,"h":20,"orientation":"horizontal"},{"text":"RECYCLE","x":2243,"y":204,"w":110,"h":20,"orientation":"horizontal"},{"text":"PUMPS","x":2373,"y":204,"w":87,"h":20,"orientation":"horizontal"},{"text":"RATED","x":2176,"y":228,"w":58,"h":22,"orientation":"horizontal"},{"text":"FLOW","x":2247,"y":228,"w":50,"h":21,"orientation":"horizontal"},{"text":":","x":2298,"y":228,"w":6,"h":21,"orientation":"horizontal"},{"text":"45","x":2315,"y":228,"w":25,"h":21,"orientation":"horizontal"},{"text":"Am\u00b3","x":2352,"y":228,"w":43,"h":21,"orientation":"horizontal"},{"text":"\/","x":2398,"y":228,"w":12,"h":21,"orientation":"horizontal"},{"text":"h","x":2412,"y":228,"w":11,"h":21,"orientation":"horizontal"},{"text":"P","x":2575,"y":175,"w":16,"h":21,"orientation":"horizontal"},{"text":"-","x":2594,"y":175,"w":16,"h":21,"orientation":"horizontal"},{"text":"6270","x":2615,"y":175,"w":64,"h":21,"orientation":"horizontal"},{"text":"A","x":2695,"y":175,"w":18,"h":21,"orientation":"horizontal"},{"text":"\/","x":2714,"y":175,"w":16,"h":21,"orientation":"horizontal"},{"text":"B","x":2730,"y":175,"w":17,"h":21,"orientation":"horizontal"},{"text":"SLOP","x":2526,"y":204,"w":64,"h":19,"orientation":"horizontal"},{"text":"WATER","x":2608,"y":204,"w":82,"h":19,"orientation":"horizontal"},{"text":"PUMPS","x":2709,"y":204,"w":88,"h":19,"orientation":"horizontal"},{"text":"RATED","x":2528,"y":228,"w":58,"h":22,"orientation":"horizontal"},{"text":"FLOW","x":2599,"y":228,"w":50,"h":21,"orientation":"horizontal"},{"text":":","x":2648,"y":228,"w":7,"h":21,"orientation":"horizontal"},{"text":"25","x":2668,"y":228,"w":25,"h":21,"orientation":"horizontal"},{"text":"Am\u00b3","x":2705,"y":228,"w":44,"h":21,"orientation":"horizontal"},{"text":"\/","x":2750,"y":228,"w":13,"h":21,"orientation":"horizontal"},{"text":"h","x":2763,"y":227,"w":11,"h":21,"orientation":"horizontal"},{"text":"\u2611","x":1802,"y":827,"w":37,"h":43,"orientation":"vertical"},{"text":"OFF","x":1589,"y":1432,"w":37,"h":14,"orientation":"horizontal"},{"text":"-","x":1627,"y":1432,"w":12,"h":14,"orientation":"horizontal"},{"text":"SPEC","x":1641,"y":1432,"w":50,"h":14,"orientation":"horizontal"},{"text":"OIL","x":1705,"y":1432,"w":30,"h":14,"orientation":"horizontal"},{"text":"HEADER","x":1748,"y":1432,"w":73,"h":14,"orientation":"horizontal"},{"text":"SLOP","x":1589,"y":1510,"w":50,"h":14,"orientation":"horizontal"},{"text":"WATER","x":1651,"y":1510,"w":62,"h":14,"orientation":"horizontal"},{"text":"HEADER","x":1726,"y":1510,"w":74,"h":14,"orientation":"horizontal"},{"text":"608","x":1958,"y":868,"w":30,"h":13,"orientation":"horizontal"},{"text":"VG","x":2095,"y":797,"w":25,"h":14,"orientation":"horizontal"},{"text":"07-001-01","x":2050,"y":816,"w":115,"h":17,"orientation":"horizontal"},{"text":"T","x":1869,"y":978,"w":15,"h":19,"orientation":"horizontal"},{"text":"-","x":1884,"y":978,"w":15,"h":19,"orientation":"horizontal"},{"text":"6110","x":1905,"y":978,"w":65,"h":19,"orientation":"horizontal"},{"text":"RECYCLED","x":1591,"y":1588,"w":95,"h":15,"orientation":"horizontal"},{"text":"EMULSION","x":1701,"y":1588,"w":93,"h":15,"orientation":"horizontal"},{"text":"HEADER","x":1810,"y":1588,"w":73,"h":15,"orientation":"horizontal"},{"text":"SLOP","x":1589,"y":1667,"w":50,"h":14,"orientation":"horizontal"},{"text":"OIL","x":1652,"y":1667,"w":30,"h":14,"orientation":"horizontal"},{"text":"HEADER","x":1695,"y":1667,"w":74,"h":14,"orientation":"horizontal"},{"text":"LLP","x":1660,"y":1768,"w":33,"h":13,"orientation":"horizontal"},{"text":"BG","x":1708,"y":1768,"w":25,"h":13,"orientation":"horizontal"},{"text":"07-002-01","x":1640,"y":1787,"w":115,"h":17,"orientation":"horizontal"},{"text":"613","x":1959,"y":1797,"w":29,"h":15,"orientation":"horizontal"},{"text":"GX","x":1673,"y":1879,"w":26,"h":42,"orientation":"horizontal"},{"text":"HGL","x":1678,"y":2159,"w":37,"h":14,"orientation":"horizontal"},{"text":"07-003-01","x":1639,"y":2180,"w":116,"h":15,"orientation":"horizontal"},{"text":"TC","x":1848,"y":1960,"w":16,"h":14,"orientation":"horizontal"},{"text":"T","x":1869,"y":1903,"w":15,"h":19,"orientation":"horizontal"},{"text":"-","x":1884,"y":1902,"w":15,"h":19,"orientation":"horizontal"},{"text":"6210","x":1905,"y":1902,"w":66,"h":19,"orientation":"horizontal"},{"text":"VG","x":2095,"y":1731,"w":25,"h":15,"orientation":"horizontal"},{"text":"07-001-01","x":2049,"y":1751,"w":118,"h":17,"orientation":"horizontal"},{"text":"\u261188","x":2107,"y":2132,"w":71,"h":33,"orientation":"horizontal"},{"text":"LLP","x":2391,"y":1766,"w":33,"h":16,"orientation":"horizontal"},{"text":"BG","x":2438,"y":1768,"w":26,"h":15,"orientation":"horizontal"},{"text":"07-002-01","x":2369,"y":1789,"w":116,"h":14,"orientation":"horizontal"},{"text":"2","x":2525,"y":1752,"w":44,"h":40,"orientation":"horizontal"},{"text":".","x":2556,"y":1751,"w":25,"h":40,"orientation":"horizontal"},{"text":"614","x":2688,"y":1797,"w":30,"h":15,"orientation":"horizontal"},{"text":"\u601d","x":2393,"y":1878,"w":47,"h":45,"orientation":"horizontal"},{"text":"TC","x":2578,"y":1961,"w":18,"h":13,"orientation":"horizontal"},{"text":"HGL","x":2408,"y":2159,"w":36,"h":15,"orientation":"horizontal"},{"text":"07-003-01","x":2370,"y":2178,"w":116,"h":17,"orientation":"horizontal"},{"text":"T","x":2599,"y":1903,"w":14,"h":19,"orientation":"horizontal"},{"text":"-","x":2615,"y":1903,"w":13,"h":19,"orientation":"horizontal"},{"text":"6220","x":2636,"y":1903,"w":64,"h":19,"orientation":"horizontal"},{"text":"E","x":3021,"y":175,"w":15,"h":19,"orientation":"horizontal"},{"text":"-","x":3037,"y":175,"w":14,"h":19,"orientation":"horizontal"},{"text":"6280","x":3059,"y":175,"w":64,"h":19,"orientation":"horizontal"},{"text":"SLOP","x":2868,"y":203,"w":67,"h":21,"orientation":"horizontal"},{"text":"OIL","x":2952,"y":203,"w":40,"h":21,"orientation":"horizontal"},{"text":"\/","x":2993,"y":203,"w":16,"h":21,"orientation":"horizontal"},{"text":"GLYCOL","x":3010,"y":203,"w":96,"h":21,"orientation":"horizontal"},{"text":"EXCHANGER","x":3124,"y":203,"w":150,"h":21,"orientation":"horizontal"},{"text":"DESIGN","x":2940,"y":232,"w":67,"h":18,"orientation":"horizontal"},{"text":"DUTY","x":3022,"y":232,"w":47,"h":18,"orientation":"horizontal"},{"text":":","x":3069,"y":232,"w":6,"h":18,"orientation":"horizontal"},{"text":"4.98","x":3087,"y":232,"w":43,"h":18,"orientation":"horizontal"},{"text":"GJ","x":3144,"y":232,"w":23,"h":18,"orientation":"horizontal"},{"text":"\/","x":3167,"y":232,"w":13,"h":18,"orientation":"horizontal"},{"text":"h","x":3181,"y":232,"w":11,"h":18,"orientation":"horizontal"},{"text":".","x":3189,"y":232,"w":8,"h":18,"orientation":"horizontal"},{"text":"SALES","x":3093,"y":789,"w":15,"h":58,"orientation":"vertical"},{"text":"OIL","x":3093,"y":744,"w":15,"h":30,"orientation":"vertical"},{"text":"MINIMUM","x":3093,"y":651,"w":17,"h":80,"orientation":"vertical"},{"text":"FLOW","x":3094,"y":588,"w":15,"h":50,"orientation":"vertical"},{"text":"\u0391\u0399","x":3212,"y":644,"w":14,"h":13,"orientation":"horizontal"},{"text":"P","x":3326,"y":175,"w":17,"h":23,"orientation":"horizontal"},{"text":"-","x":3346,"y":175,"w":16,"h":23,"orientation":"horizontal"},{"text":"6155","x":3367,"y":175,"w":63,"h":23,"orientation":"horizontal"},{"text":"\/","x":3432,"y":175,"w":17,"h":23,"orientation":"horizontal"},{"text":"P","x":3451,"y":175,"w":15,"h":23,"orientation":"horizontal"},{"text":"-","x":3468,"y":175,"w":17,"h":23,"orientation":"horizontal"},{"text":"6160","x":3489,"y":175,"w":65,"h":23,"orientation":"horizontal"},{"text":"\/","x":3555,"y":175,"w":18,"h":23,"orientation":"horizontal"},{"text":"P","x":3573,"y":175,"w":16,"h":23,"orientation":"horizontal"},{"text":"-","x":3591,"y":175,"w":15,"h":23,"orientation":"horizontal"},{"text":"6165","x":3612,"y":175,"w":65,"h":23,"orientation":"horizontal"},{"text":"SALES","x":3324,"y":204,"w":76,"h":19,"orientation":"horizontal"},{"text":"OIL","x":3420,"y":204,"w":38,"h":19,"orientation":"horizontal"},{"text":"SAMPLE","x":3476,"y":204,"w":97,"h":19,"orientation":"horizontal"},{"text":"PUMPS","x":3592,"y":204,"w":87,"h":19,"orientation":"horizontal"},{"text":"RATED","x":3369,"y":229,"w":59,"h":20,"orientation":"horizontal"},{"text":"FLOW","x":3441,"y":229,"w":49,"h":20,"orientation":"horizontal"},{"text":":","x":3492,"y":229,"w":6,"h":20,"orientation":"horizontal"},{"text":"3.4","x":3511,"y":229,"w":31,"h":20,"orientation":"horizontal"},{"text":"Am\u00b3","x":3553,"y":229,"w":44,"h":20,"orientation":"horizontal"},{"text":"\/","x":3598,"y":229,"w":13,"h":20,"orientation":"horizontal"},{"text":"h","x":3611,"y":229,"w":11,"h":20,"orientation":"horizontal"},{"text":"P","x":4232,"y":176,"w":15,"h":19,"orientation":"horizontal"},{"text":"-","x":4250,"y":176,"w":15,"h":19,"orientation":"horizontal"},{"text":"6260","x":4272,"y":176,"w":64,"h":19,"orientation":"horizontal"},{"text":"SLOP","x":4149,"y":204,"w":65,"h":19,"orientation":"horizontal"},{"text":"SYSTEM","x":4233,"y":204,"w":94,"h":19,"orientation":"horizontal"},{"text":"PUMP","x":4347,"y":204,"w":71,"h":19,"orientation":"horizontal"},{"text":"RATED","x":4151,"y":228,"w":59,"h":21,"orientation":"horizontal"},{"text":"FLOW","x":4223,"y":228,"w":51,"h":21,"orientation":"horizontal"},{"text":":","x":4273,"y":228,"w":7,"h":21,"orientation":"horizontal"},{"text":"5","x":4292,"y":228,"w":13,"h":21,"orientation":"horizontal"},{"text":"Am","x":4316,"y":228,"w":29,"h":21,"orientation":"horizontal"},{"text":"\u00b3","x":4353,"y":228,"w":15,"h":21,"orientation":"horizontal"},{"text":"\/","x":4362,"y":228,"w":13,"h":21,"orientation":"horizontal"},{"text":"h","x":4374,"y":228,"w":12,"h":21,"orientation":"horizontal"},{"text":"PLANT","x":4522,"y":200,"w":58,"h":14,"orientation":"horizontal"},{"text":"LIMIT","x":4594,"y":200,"w":45,"h":14,"orientation":"horizontal"},{"text":"NNF","x":3702,"y":257,"w":37,"h":15,"orientation":"horizontal"},{"text":"DENS","x":3240,"y":616,"w":48,"h":16,"orientation":"horizontal"},{"text":"COARSE","x":3350,"y":604,"w":73,"h":14,"orientation":"horizontal"},{"text":"DILUENT","x":3351,"y":623,"w":74,"h":15,"orientation":"horizontal"},{"text":"RATIO","x":3520,"y":603,"w":51,"h":17,"orientation":"horizontal"},{"text":"FINE","x":3702,"y":604,"w":40,"h":13,"orientation":"horizontal"},{"text":"RATIO","x":3878,"y":605,"w":49,"h":13,"orientation":"horizontal"},{"text":"FC","x":3483,"y":617,"w":20,"h":14,"orientation":"horizontal"},{"text":"FI","x":3304,"y":644,"w":13,"h":13,"orientation":"horizontal"},{"text":"|","x":3342,"y":641,"w":5,"h":18,"orientation":"horizontal"},{"text":"CONTROL","x":3350,"y":641,"w":87,"h":18,"orientation":"horizontal"},{"text":"1","x":3669,"y":622,"w":10,"h":15,"orientation":"horizontal"},{"text":"DILUENT","x":3700,"y":621,"w":79,"h":17,"orientation":"horizontal"},{"text":"||","x":3671,"y":641,"w":26,"h":18,"orientation":"horizontal"},{"text":"CONTROL","x":3700,"y":640,"w":88,"h":19,"orientation":"horizontal"},{"text":"FC","x":3841,"y":616,"w":19,"h":16,"orientation":"horizontal"},{"text":"DENS","x":3606,"y":867,"w":50,"h":15,"orientation":"horizontal"},{"text":"AC","x":3665,"y":900,"w":20,"h":13,"orientation":"horizontal"},{"text":"\u0391\u0399","x":3721,"y":900,"w":13,"h":14,"orientation":"horizontal"},{"text":"DENS","x":3291,"y":971,"w":49,"h":15,"orientation":"horizontal"},{"text":"VIS","x":3431,"y":972,"w":28,"h":13,"orientation":"horizontal"},{"text":"\u0391\u0399","x":3354,"y":1004,"w":12,"h":14,"orientation":"horizontal"},{"text":"\u0391\u0399","x":3406,"y":1004,"w":13,"h":14,"orientation":"horizontal"},{"text":"P","x":3571,"y":1024,"w":16,"h":18,"orientation":"horizontal"},{"text":"-","x":3589,"y":1024,"w":15,"h":18,"orientation":"horizontal"},{"text":"6160","x":3611,"y":1024,"w":65,"h":18,"orientation":"horizontal"},{"text":"FC","x":3020,"y":1119,"w":19,"h":14,"orientation":"horizontal"},{"text":"P","x":3257,"y":1127,"w":15,"h":18,"orientation":"horizontal"},{"text":"-","x":3275,"y":1127,"w":15,"h":18,"orientation":"horizontal"},{"text":"6155","x":3296,"y":1127,"w":64,"h":19,"orientation":"horizontal"},{"text":"P","x":2945,"y":1270,"w":16,"h":23,"orientation":"horizontal"},{"text":"-","x":2964,"y":1270,"w":16,"h":23,"orientation":"horizontal"},{"text":"6150","x":2984,"y":1270,"w":65,"h":23,"orientation":"horizontal"},{"text":"A","x":3064,"y":1270,"w":19,"h":23,"orientation":"horizontal"},{"text":"\/","x":3083,"y":1270,"w":16,"h":23,"orientation":"horizontal"},{"text":"B","x":3100,"y":1270,"w":15,"h":23,"orientation":"horizontal"},{"text":"\/","x":3117,"y":1271,"w":17,"h":23,"orientation":"horizontal"},{"text":"C","x":3134,"y":1271,"w":19,"h":23,"orientation":"horizontal"},{"text":"HI","x":2959,"y":1387,"w":10,"h":13,"orientation":"horizontal"},{"text":"NOTE","x":3018,"y":1303,"w":46,"h":16,"orientation":"horizontal"},{"text":"3","x":3079,"y":1303,"w":11,"h":14,"orientation":"horizontal"},{"text":"VG","x":2825,"y":1732,"w":24,"h":13,"orientation":"horizontal"},{"text":"07-001-01","x":2780,"y":1753,"w":116,"h":14,"orientation":"horizontal"},{"text":"VG","x":3555,"y":1732,"w":26,"h":14,"orientation":"horizontal"},{"text":"07-001-01","x":3510,"y":1750,"w":117,"h":18,"orientation":"horizontal"},{"text":"LLP","x":3120,"y":1767,"w":32,"h":15,"orientation":"horizontal"},{"text":"BG","x":3167,"y":1767,"w":26,"h":14,"orientation":"horizontal"},{"text":"07-002-01","x":3100,"y":1789,"w":115,"h":14,"orientation":"horizontal"},{"text":"615","x":3419,"y":1796,"w":27,"h":16,"orientation":"horizontal"},{"text":"\u7085","x":3125,"y":1879,"w":42,"h":44,"orientation":"horizontal"},{"text":"T","x":3328,"y":1903,"w":15,"h":19,"orientation":"horizontal"},{"text":"-","x":3344,"y":1902,"w":13,"h":19,"orientation":"horizontal"},{"text":"6230","x":3365,"y":1902,"w":64,"h":19,"orientation":"horizontal"},{"text":"TC","x":3308,"y":1960,"w":18,"h":14,"orientation":"horizontal"},{"text":"888","x":2837,"y":2131,"w":72,"h":34,"orientation":"horizontal"},{"text":"HGL","x":3138,"y":2159,"w":36,"h":15,"orientation":"horizontal"},{"text":"07-003-01","x":3099,"y":2178,"w":118,"h":16,"orientation":"horizontal"},{"text":"\u2611","x":3206,"y":2546,"w":27,"h":17,"orientation":"horizontal"},{"text":"603","x":4423,"y":538,"w":28,"h":14,"orientation":"horizontal"},{"text":"OFF","x":4672,"y":249,"w":38,"h":16,"orientation":"horizontal"},{"text":"SPEC","x":4724,"y":249,"w":51,"h":16,"orientation":"horizontal"},{"text":"OIL","x":4788,"y":249,"w":30,"h":17,"orientation":"horizontal"},{"text":"FROM","x":4674,"y":303,"w":50,"h":15,"orientation":"horizontal"},{"text":"LACT","x":4740,"y":303,"w":44,"h":15,"orientation":"horizontal"},{"text":"UNIT","x":4798,"y":303,"w":41,"h":15,"orientation":"horizontal"},{"text":"PLANT","x":4523,"y":643,"w":56,"h":14,"orientation":"horizontal"},{"text":"LIMIT","x":4595,"y":643,"w":44,"h":14,"orientation":"horizontal"},{"text":"DILUENT","x":4674,"y":511,"w":76,"h":14,"orientation":"horizontal"},{"text":"TL1-42","x":4692,"y":537,"w":57,"h":16,"orientation":"horizontal"},{"text":"-","x":4751,"y":537,"w":9,"h":15,"orientation":"horizontal"},{"text":"PFD","x":4764,"y":537,"w":29,"h":15,"orientation":"horizontal"},{"text":"-","x":4794,"y":537,"w":10,"h":15,"orientation":"horizontal"},{"text":"06-001-01","x":4805,"y":537,"w":95,"h":15,"orientation":"horizontal"},{"text":"FROM","x":4674,"y":564,"w":50,"h":18,"orientation":"horizontal"},{"text":"E","x":4739,"y":564,"w":12,"h":18,"orientation":"horizontal"},{"text":"-","x":4751,"y":564,"w":13,"h":18,"orientation":"horizontal"},{"text":"4020","x":4766,"y":564,"w":50,"h":18,"orientation":"horizontal"},{"text":"A","x":4828,"y":564,"w":14,"h":18,"orientation":"horizontal"},{"text":"\/","x":4841,"y":564,"w":13,"h":18,"orientation":"horizontal"},{"text":"B","x":4855,"y":564,"w":12,"h":18,"orientation":"horizontal"},{"text":",","x":4867,"y":564,"w":6,"h":18,"orientation":"horizontal"},{"text":"DILUENT","x":4673,"y":587,"w":76,"h":17,"orientation":"horizontal"},{"text":"\/","x":4750,"y":587,"w":12,"h":17,"orientation":"horizontal"},{"text":"GLYCOL","x":4764,"y":587,"w":72,"h":17,"orientation":"horizontal"},{"text":"EXCHANGERS","x":4849,"y":587,"w":126,"h":17,"orientation":"horizontal"},{"text":"PHASE","x":4701,"y":606,"w":61,"h":21,"orientation":"horizontal"},{"text":"A","x":4773,"y":608,"w":15,"h":19,"orientation":"horizontal"},{"text":"\/","x":4785,"y":608,"w":13,"h":19,"orientation":"horizontal"},{"text":"B","x":4801,"y":608,"w":12,"h":19,"orientation":"horizontal"},{"text":"SALES","x":4659,"y":693,"w":57,"h":14,"orientation":"horizontal"},{"text":"OIL","x":4730,"y":693,"w":28,"h":14,"orientation":"horizontal"},{"text":"TO","x":4658,"y":746,"w":23,"h":16,"orientation":"horizontal"},{"text":"LACT","x":4695,"y":746,"w":44,"h":15,"orientation":"horizontal"},{"text":"UNIT","x":4753,"y":746,"w":41,"h":15,"orientation":"horizontal"},{"text":"609","x":4587,"y":719,"w":30,"h":18,"orientation":"horizontal"},{"text":"DENS","x":3932,"y":749,"w":48,"h":15,"orientation":"horizontal"},{"text":"VIS","x":4072,"y":750,"w":29,"h":14,"orientation":"horizontal"},{"text":"BS","x":4472,"y":755,"w":23,"h":13,"orientation":"horizontal"},{"text":"&","x":4497,"y":755,"w":13,"h":13,"orientation":"horizontal"},{"text":"W","x":4512,"y":755,"w":15,"h":13,"orientation":"horizontal"},{"text":"\u0391\u0399","x":4445,"y":781,"w":13,"h":13,"orientation":"horizontal"},{"text":"AC","x":3991,"y":780,"w":20,"h":15,"orientation":"horizontal"},{"text":"\u0391\u0399","x":4047,"y":780,"w":13,"h":14,"orientation":"horizontal"},{"text":"VIS","x":3743,"y":868,"w":30,"h":13,"orientation":"horizontal"},{"text":"E","x":4046,"y":865,"w":15,"h":18,"orientation":"horizontal"},{"text":"-","x":4063,"y":865,"w":14,"h":18,"orientation":"horizontal"},{"text":"6160","x":4084,"y":865,"w":64,"h":18,"orientation":"horizontal"},{"text":"P","x":3898,"y":911,"w":15,"h":19,"orientation":"horizontal"},{"text":"-","x":3914,"y":910,"w":15,"h":19,"orientation":"horizontal"},{"text":"6165","x":3936,"y":909,"w":64,"h":20,"orientation":"horizontal"},{"text":"Fl","x":4048,"y":1146,"w":12,"h":14,"orientation":"horizontal"},{"text":"P","x":3885,"y":1282,"w":16,"h":22,"orientation":"horizontal"},{"text":"-","x":3903,"y":1282,"w":16,"h":22,"orientation":"horizontal"},{"text":"6270","x":3924,"y":1282,"w":64,"h":23,"orientation":"horizontal"},{"text":"A","x":4005,"y":1283,"w":19,"h":22,"orientation":"horizontal"},{"text":"\/","x":4021,"y":1283,"w":18,"h":22,"orientation":"horizontal"},{"text":"B","x":4040,"y":1283,"w":17,"h":22,"orientation":"horizontal"},{"text":"888","x":4282,"y":1826,"w":74,"h":42,"orientation":"horizontal"},{"text":"SC","x":4466,"y":1882,"w":20,"h":14,"orientation":"horizontal"},{"text":"FO","x":4017,"y":1914,"w":21,"h":14,"orientation":"horizontal"},{"text":"P","x":3878,"y":2078,"w":15,"h":22,"orientation":"horizontal"},{"text":"-","x":3897,"y":2078,"w":15,"h":22,"orientation":"horizontal"},{"text":"6250","x":3917,"y":2077,"w":65,"h":24,"orientation":"horizontal"},{"text":"A","x":3997,"y":2079,"w":19,"h":22,"orientation":"horizontal"},{"text":"\/","x":4015,"y":2079,"w":17,"h":22,"orientation":"horizontal"},{"text":"B","x":4034,"y":2079,"w":17,"h":22,"orientation":"horizontal"},{"text":"888","x":3566,"y":2130,"w":74,"h":37,"orientation":"horizontal"},{"text":"TC","x":3582,"y":2471,"w":17,"h":13,"orientation":"horizontal"},{"text":"E","x":3715,"y":2574,"w":15,"h":20,"orientation":"horizontal"},{"text":"-","x":3731,"y":2573,"w":14,"h":20,"orientation":"horizontal"},{"text":"6280","x":3752,"y":2573,"w":65,"h":20,"orientation":"horizontal"},{"text":"HGL","x":3680,"y":2635,"w":34,"h":14,"orientation":"horizontal"},{"text":"07-003-01","x":3641,"y":2654,"w":117,"h":16,"orientation":"horizontal"},{"text":"NC","x":3683,"y":2723,"w":25,"h":14,"orientation":"horizontal"},{"text":"FC","x":3868,"y":2471,"w":18,"h":13,"orientation":"horizontal"},{"text":"PC","x":3999,"y":2471,"w":21,"h":13,"orientation":"horizontal"},{"text":"DATE","x":4134,"y":3009,"w":44,"h":14,"orientation":"horizontal"},{"text":":","x":4179,"y":3009,"w":5,"h":14,"orientation":"horizontal"},{"text":"611","x":4549,"y":1207,"w":26,"h":17,"orientation":"horizontal"},{"text":"P","x":4413,"y":2079,"w":15,"h":19,"orientation":"horizontal"},{"text":"-","x":4430,"y":2079,"w":14,"h":19,"orientation":"horizontal"},{"text":"6260","x":4452,"y":2079,"w":65,"h":19,"orientation":"horizontal"},{"text":"NNF","x":4589,"y":2136,"w":38,"h":14,"orientation":"horizontal"},{"text":"OFF","x":4216,"y":2143,"w":36,"h":14,"orientation":"horizontal"},{"text":"-","x":4253,"y":2143,"w":14,"h":14,"orientation":"horizontal"},{"text":"SPEC","x":4268,"y":2143,"w":50,"h":14,"orientation":"horizontal"},{"text":"OIL","x":4332,"y":2143,"w":29,"h":14,"orientation":"horizontal"},{"text":"HEADER","x":4374,"y":2143,"w":75,"h":14,"orientation":"horizontal"},{"text":"SLOP","x":4216,"y":2272,"w":49,"h":16,"orientation":"horizontal"},{"text":"OIL","x":4279,"y":2272,"w":30,"h":16,"orientation":"horizontal"},{"text":"HEADER","x":4321,"y":2272,"w":74,"h":18,"orientation":"horizontal"},{"text":"610","x":4591,"y":2285,"w":29,"h":14,"orientation":"horizontal"},{"text":"RECYCLED","x":4217,"y":2403,"w":95,"h":15,"orientation":"horizontal"},{"text":"EMULSION","x":4327,"y":2403,"w":94,"h":15,"orientation":"horizontal"},{"text":"cenovus","x":2844,"y":3036,"w":289,"h":54,"orientation":"horizontal"},{"text":"ENERGY","x":2968,"y":3092,"w":159,"h":15,"orientation":"horizontal"},{"text":"Cenovus","x":2887,"y":3155,"w":105,"h":18,"orientation":"horizontal"},{"text":"TL","x":3000,"y":3155,"w":30,"h":18,"orientation":"horizontal"},{"text":"ULC","x":3038,"y":3155,"w":51,"h":18,"orientation":"horizontal"},{"text":"Telephone","x":2849,"y":3184,"w":122,"h":21,"orientation":"horizontal"},{"text":"Lake","x":2979,"y":3184,"w":57,"h":21,"orientation":"horizontal"},{"text":"Project","x":3043,"y":3184,"w":85,"h":21,"orientation":"horizontal"},{"text":"Process","x":3438,"y":3024,"w":178,"h":46,"orientation":"horizontal"},{"text":"Flow","x":3633,"y":3027,"w":101,"h":45,"orientation":"horizontal"},{"text":"Diagram","x":3753,"y":3029,"w":184,"h":45,"orientation":"horizontal"},{"text":"Sales","x":3411,"y":3085,"w":125,"h":43,"orientation":"horizontal"},{"text":"and","x":3550,"y":3085,"w":81,"h":43,"orientation":"horizontal"},{"text":"Slop","x":3646,"y":3085,"w":100,"h":43,"orientation":"horizontal"},{"text":"Oil","x":3762,"y":3085,"w":60,"h":43,"orientation":"horizontal"},{"text":"Tanks","x":3836,"y":3085,"w":129,"h":43,"orientation":"horizontal"},{"text":"Phases","x":3513,"y":3142,"w":164,"h":35,"orientation":"horizontal"},{"text":"A","x":3690,"y":3142,"w":34,"h":35,"orientation":"horizontal"},{"text":"and","x":3735,"y":3142,"w":83,"h":35,"orientation":"horizontal"},{"text":"B","x":3835,"y":3142,"w":31,"h":35,"orientation":"horizontal"},{"text":"December","x":4148,"y":3036,"w":128,"h":20,"orientation":"horizontal"},{"text":"2011","x":4283,"y":3036,"w":55,"h":20,"orientation":"horizontal"},{"text":"PROJECT","x":4134,"y":3085,"w":79,"h":13,"orientation":"horizontal"},{"text":":","x":4213,"y":3085,"w":5,"h":13,"orientation":"horizontal"},{"text":"CE0339901","x":4148,"y":3110,"w":143,"h":22,"orientation":"horizontal"},{"text":"ANALYST","x":4134,"y":3157,"w":75,"h":14,"orientation":"horizontal"},{"text":":","x":4207,"y":3157,"w":5,"h":13,"orientation":"horizontal"},{"text":"QA","x":4237,"y":3157,"w":24,"h":14,"orientation":"horizontal"},{"text":"\/","x":4261,"y":3157,"w":7,"h":14,"orientation":"horizontal"},{"text":"QC","x":4267,"y":3157,"w":25,"h":14,"orientation":"horizontal"},{"text":":","x":4293,"y":3157,"w":4,"h":14,"orientation":"horizontal"},{"text":"KW","x":4147,"y":3179,"w":43,"h":22,"orientation":"horizontal"},{"text":"KW","x":4263,"y":3182,"w":41,"h":19,"orientation":"horizontal"},{"text":"EH","x":4334,"y":3182,"w":35,"h":19,"orientation":"horizontal"},{"text":"EH","x":4401,"y":3182,"w":35,"h":19,"orientation":"horizontal"},{"text":"RECYCLED","x":4660,"y":1182,"w":95,"h":14,"orientation":"horizontal"},{"text":"PRODUCED","x":4770,"y":1182,"w":103,"h":14,"orientation":"horizontal"},{"text":"WATER","x":4886,"y":1182,"w":61,"h":14,"orientation":"horizontal"},{"text":"TL1-42","x":4708,"y":1209,"w":59,"h":14,"orientation":"horizontal"},{"text":"-","x":4768,"y":1209,"w":10,"h":14,"orientation":"horizontal"},{"text":"PFD","x":4781,"y":1209,"w":28,"h":14,"orientation":"horizontal"},{"text":"-","x":4811,"y":1209,"w":10,"h":14,"orientation":"horizontal"},{"text":"01-001-02","x":4822,"y":1209,"w":96,"h":14,"orientation":"horizontal"},{"text":"TO","x":4658,"y":1236,"w":24,"h":16,"orientation":"horizontal"},{"text":"T","x":4695,"y":1236,"w":11,"h":16,"orientation":"horizontal"},{"text":"-","x":4707,"y":1236,"w":11,"h":16,"orientation":"horizontal"},{"text":"1400","x":4723,"y":1236,"w":48,"h":16,"orientation":"horizontal"},{"text":",","x":4772,"y":1236,"w":5,"h":16,"orientation":"horizontal"},{"text":"SKIM","x":4791,"y":1236,"w":44,"h":16,"orientation":"horizontal"},{"text":"TANK","x":4848,"y":1236,"w":49,"h":16,"orientation":"horizontal"},{"text":"OFF","x":4659,"y":2127,"w":37,"h":15,"orientation":"horizontal"},{"text":"-","x":4696,"y":2127,"w":12,"h":15,"orientation":"horizontal"},{"text":"SPEC","x":4710,"y":2127,"w":51,"h":15,"orientation":"horizontal"},{"text":"OIL","x":4774,"y":2127,"w":30,"h":15,"orientation":"horizontal"},{"text":"TL1-42","x":4708,"y":2155,"w":60,"h":14,"orientation":"horizontal"},{"text":"-","x":4769,"y":2155,"w":10,"h":14,"orientation":"horizontal"},{"text":"PFD","x":4782,"y":2155,"w":29,"h":14,"orientation":"horizontal"},{"text":"-","x":4813,"y":2155,"w":10,"h":14,"orientation":"horizontal"},{"text":"04-001-01","x":4824,"y":2155,"w":93,"h":14,"orientation":"horizontal"},{"text":"TO","x":4658,"y":2182,"w":24,"h":16,"orientation":"horizontal"},{"text":"V","x":4694,"y":2182,"w":13,"h":16,"orientation":"horizontal"},{"text":"-","x":4708,"y":2182,"w":12,"h":16,"orientation":"horizontal"},{"text":"4100","x":4722,"y":2182,"w":50,"h":16,"orientation":"horizontal"},{"text":"\/","x":4774,"y":2182,"w":11,"h":16,"orientation":"horizontal"},{"text":"4300","x":4786,"y":2182,"w":49,"h":16,"orientation":"horizontal"},{"text":",","x":4836,"y":2182,"w":6,"h":16,"orientation":"horizontal"},{"text":"FWKO","x":4660,"y":2202,"w":52,"h":18,"orientation":"horizontal"},{"text":"DRUM","x":4726,"y":2202,"w":53,"h":18,"orientation":"horizontal"},{"text":"V","x":4791,"y":2202,"w":14,"h":18,"orientation":"horizontal"},{"text":"-","x":4805,"y":2202,"w":13,"h":18,"orientation":"horizontal"},{"text":"4150","x":4819,"y":2202,"w":50,"h":18,"orientation":"horizontal"},{"text":"\/","x":4870,"y":2202,"w":13,"h":18,"orientation":"horizontal"},{"text":"4350","x":4883,"y":2202,"w":50,"h":19,"orientation":"horizontal"},{"text":",","x":4932,"y":2203,"w":6,"h":18,"orientation":"horizontal"},{"text":"TREATER","x":4659,"y":2224,"w":79,"h":16,"orientation":"horizontal"},{"text":"SLOP","x":4659,"y":2258,"w":49,"h":14,"orientation":"horizontal"},{"text":"OIL","x":4721,"y":2258,"w":30,"h":14,"orientation":"horizontal"},{"text":"TL1-42","x":4708,"y":2285,"w":60,"h":15,"orientation":"horizontal"},{"text":"-","x":4769,"y":2285,"w":10,"h":15,"orientation":"horizontal"},{"text":"PFD","x":4782,"y":2285,"w":29,"h":15,"orientation":"horizontal"},{"text":"-","x":4812,"y":2285,"w":10,"h":15,"orientation":"horizontal"},{"text":"05-001-01","x":4824,"y":2285,"w":94,"h":15,"orientation":"horizontal"},{"text":"TO","x":4658,"y":2311,"w":25,"h":18,"orientation":"horizontal"},{"text":"E","x":4695,"y":2311,"w":12,"h":18,"orientation":"horizontal"},{"text":"-","x":4707,"y":2311,"w":13,"h":18,"orientation":"horizontal"},{"text":"5025","x":4723,"y":2311,"w":49,"h":18,"orientation":"horizontal"},{"text":"A","x":4785,"y":2311,"w":13,"h":18,"orientation":"horizontal"},{"text":"\/","x":4798,"y":2311,"w":13,"h":18,"orientation":"horizontal"},{"text":"B","x":4812,"y":2311,"w":11,"h":18,"orientation":"horizontal"},{"text":",","x":4825,"y":2311,"w":5,"h":18,"orientation":"horizontal"},{"text":"SLOP","x":4843,"y":2311,"w":49,"h":18,"orientation":"horizontal"},{"text":"OIL","x":4906,"y":2311,"w":30,"h":18,"orientation":"horizontal"},{"text":"TREATER","x":4659,"y":2331,"w":81,"h":18,"orientation":"horizontal"},{"text":"FEED","x":4753,"y":2331,"w":49,"h":18,"orientation":"horizontal"},{"text":"\/","x":4801,"y":2331,"w":12,"h":18,"orientation":"horizontal"},{"text":"EFFLUENT","x":4815,"y":2331,"w":93,"h":18,"orientation":"horizontal"},{"text":"EXCHANGERS","x":4660,"y":2351,"w":125,"h":14,"orientation":"horizontal"},{"text":"FigATT07-24","x":4505,"y":3004,"w":136,"h":24,"orientation":"horizontal"},{"text":"Sales","x":4648,"y":3003,"w":62,"h":23,"orientation":"horizontal"},{"text":"Tanks","x":4716,"y":3002,"w":63,"h":23,"orientation":"horizontal"},{"text":"11-12-13","x":4595,"y":3043,"w":93,"h":16,"orientation":"horizontal"},{"text":"PROJECTION","x":4470,"y":3084,"w":107,"h":15,"orientation":"horizontal"},{"text":"\/","x":4579,"y":3085,"w":6,"h":13,"orientation":"horizontal"},{"text":"DATUM","x":4586,"y":3085,"w":57,"h":13,"orientation":"horizontal"},{"text":":","x":4644,"y":3085,"w":5,"h":13,"orientation":"horizontal"},{"text":"UTM","x":4484,"y":3112,"w":57,"h":20,"orientation":"horizontal"},{"text":"Zone","x":4550,"y":3112,"w":61,"h":20,"orientation":"horizontal"},{"text":"12","x":4623,"y":3112,"w":28,"h":20,"orientation":"horizontal"},{"text":"NAD83","x":4668,"y":3112,"w":88,"h":20,"orientation":"horizontal"},{"text":"PROVIDED","x":4470,"y":3158,"w":87,"h":12,"orientation":"horizontal"},{"text":"BY","x":4565,"y":3158,"w":22,"h":12,"orientation":"horizontal"},{"text":":","x":4585,"y":3158,"w":6,"h":12,"orientation":"horizontal"},{"text":"Cenovus","x":4500,"y":3182,"w":107,"h":19,"orientation":"horizontal"},{"text":"FINAL","x":4653,"y":3157,"w":47,"h":13,"orientation":"horizontal"},{"text":"MAPPING","x":4706,"y":3157,"w":77,"h":13,"orientation":"horizontal"},{"text":"BY","x":4791,"y":3157,"w":22,"h":13,"orientation":"horizontal"},{"text":":","x":4812,"y":3157,"w":6,"h":13,"orientation":"horizontal"},{"text":"AMEC","x":4696,"y":3181,"w":80,"h":19,"orientation":"horizontal"},{"text":"Figure","x":4853,"y":3063,"w":134,"h":38,"orientation":"horizontal"},{"text":"ATT7-24","x":4832,"y":3121,"w":173,"h":32,"orientation":"horizontal"}]